[
  {
    "id": 1,
    "guid": "3233933",
    "title": "Einigung auf Standards - Bezahlkarte für Asylwerber kommt deutschlandweit",
    "description": "Jetzt ist es fix: In Deutschland wird bundesweit eine Bezahlkarte für Asylwerber eingeführt. Damit s...",
    "author": "Krone",
    "date": "2024-01-31 17:19",
    "comments": 11,
    "likes": 59,
    "link": "https://www.krone.at/3233933",
    "image": "https://imgl.krone.at/scaled/729229/v14c8b7/full.jpg",
    "isAd": false
  },
  {
    "id": 2,
    "guid": "3233799",
    "title": "Republik will Geld - Jetzt Insolvenzantrag gegen René Benko persönlich",
    "description": "Jetzt wird offenbar auch René Benko selbst in den Insolvenzstrudel seines Signa-Imperiums gerissen: ...",
    "author": "Krone",
    "date": "2024-01-31 16:41",
    "comments": 22,
    "likes": 193,
    "link": "https://www.krone.at/3233799",
    "image": "https://imgl.krone.at/scaled/2257341/vc815ca/full.jpg",
    "isAd": false
  },
  {
    "id": 3,
    "guid": "3233414",
    "title": "Fall Jack Unterweger - „11 Frauen bezahlten Justizgroteske mit dem Leben“",
    "description": "30 Jahre nach seinem Tod erregt der Fall Jack Unterweger weiter die Gemüter. Hofiert von Politik und...",
    "author": "Krone",
    "date": "2024-01-31 17:33",
    "comments": 1,
    "likes": 9,
    "link": "https://www.krone.at/3233414",
    "image": "https://imgl.krone.at/scaled/3233393/ve4a46a/full.jpg",
    "isAd": false
  },
  {
    "id": 4,
    "guid": "3233577",
    "title": "Alte Sicherheitslücke - Wie drei Identitäre aufs Dach des Parlaments kamen",
    "description": "Zehntausende Menschen waren am vergangenen Freitag in Wien und in den Landeshauptstädten auf die Str...",
    "author": "Krone",
    "date": "2024-01-31 15:59",
    "comments": 7,
    "likes": 146,
    "link": "https://www.krone.at/3233577",
    "image": "https://imgl.krone.at/scaled/3230391/v707746/full.jpg",
    "isAd": false
  },
  {
    "id": 5,
    "guid": "3233489",
    "title": "Kickl rechtsextrem?   - Mölzer: „Das ist diffamierendes Kampfvokabel“",
    "description": "Im aktuellen „Duell“ auf krone.tv zwischen Eva Glawischnig und Andreas Mölzer geht es unter anderem ...",
    "author": "Krone",
    "date": "2024-01-31 17:00",
    "comments": 15,
    "likes": 113,
    "link": "https://www.krone.at/3233489",
    "image": "https://imgl.krone.at/scaled/3233487/vb0f8c6/full.jpg",
    "isAd": false
  },
  {
    "id": 6,
    "guid": "3233802",
    "title": "Klub-Urgesteine - Tuchel: Zu diesem Bayern-Trio hat er keinen Draht",
    "description": "Zwar konnten die Bayern am vergangenen Wochenende den Rückstand auf Tabellenführer Bayer Leverkusen ...",
    "author": "Krone",
    "date": "2024-01-31 15:42",
    "comments": 4,
    "likes": 47,
    "link": "https://www.krone.at/3233802",
    "image": "https://imgl.krone.at/scaled/3191942/v736491/full.jpg",
    "isAd": false
  },
  {
    "id": 7,
    "guid": "3233708",
    "title": "Koubek-Kolumne - Keiner kennt Dominic Thiem so gut wie sein Vater",
    "description": "„Krone“-Kolumnist Stefan Koubek hält den Trainerwechsel von Tennis-Ass Dominic Thiem für absolut nac...",
    "author": "Krone",
    "date": "2024-01-31 17:30",
    "comments": 4,
    "likes": 72,
    "link": "https://www.krone.at/3233708",
    "image": "https://imgl.krone.at/scaled/3042749/v1c1b78/full.jpg",
    "isAd": false
  },
  {
    "id": 8,
    "guid": "3233312",
    "title": "Von Russen belastet - Kurz-Prozess: Thomas Schmid wird nochmals befragt",
    "description": "Skurril endeten am Mittwoch die Zeugenbefragungen im Prozess gegen Ex-Kanzler Sebastian Kurz (ÖVP) w...",
    "author": "Krone",
    "date": "2024-01-31 16:38",
    "comments": 8,
    "likes": 102,
    "link": "https://www.krone.at/3233312",
    "image": "https://imgl.krone.at/scaled/3233532/v909f25/full.jpg",
    "isAd": false
  },
  {
    "id": 9,
    "guid": "3233787",
    "title": "Russland blockiert - Wo sind die abgestürzten Kriegsgefangenen?",
    "description": "Der angebliche Absturz von 65 ukrainischen in der russischen Grenzregion Belgorod gibt weiterhin Rät...",
    "author": "Krone",
    "date": "2024-01-31 16:11",
    "comments": 22,
    "likes": 146,
    "link": "https://www.krone.at/3233787",
    "image": "https://imgl.krone.at/scaled/3233878/vfbaa5c/full.jpg",
    "isAd": false
  },
  {
    "id": 10,
    "guid": "3234005",
    "title": "Heinz Simmet ist tot - 1. FC Köln trauert um „Kettenhund im Mittelfeld“",
    "description": "Der 1. FC Köln trauert um Heinz Simmet. Der ehemalige Mittelfeldspieler der „Geißböcke“ ist im Alter...",
    "author": "Krone",
    "date": "2024-01-31 17:02",
    "comments": 4,
    "likes": 75,
    "link": "https://www.krone.at/3234005",
    "image": "https://imgl.krone.at/scaled/3234003/v8f4867/full.jpg",
    "isAd": false
  },
  {
    "id": 11,
    "guid": "3233849",
    "title": "Mord im Copyshop - Tödlicher Schuss: „Der Boden war voller Blut!“",
    "description": "Ein verheerender Schuss oder gezielter Mord? Dieser Frage müssen sich die Geschworenen im Wiener Lan...",
    "author": "Krone",
    "date": "2024-01-31 17:11",
    "comments": 10,
    "likes": 71,
    "link": "https://www.krone.at/3233849",
    "image": "https://imgl.krone.at/scaled/3173031/v11a0c1/full.jpg",
    "isAd": false
  },
  {
    "id": 12,
    "guid": "3231496",
    "title": "Gaming-Flunder im Test - Omen Transcend 16: Wie viel Power passt in 2 Kilo?",
    "description": "Gaming-Laptops werden immer mobiler: HP spielt mit dem neuen Omen Transcend 16 in der 2,1-Kilo-Klass...",
    "author": "Krone",
    "date": "2024-01-30 17:45",
    "comments": 1,
    "likes": 115,
    "link": "https://www.krone.at/3231496",
    "image": "https://imgl.krone.at/scaled/3231657/vaed49b/full.jpg",
    "isAd": false
  },
  {
    "id": 13,
    "guid": "3233682",
    "title": "Spanier holt Silber - Herbe WM-Klatsche für Österreichs Speed-Nachwuchs",
    "description": "Während die ÖSV-Damen durch Victoria Oliviers Abfahrtsgold und die Silber- und Bronzemedaillen von V...",
    "author": "Krone",
    "date": "2024-01-31 14:25",
    "comments": 5,
    "likes": 62,
    "link": "https://www.krone.at/3233682",
    "image": "https://imgl.krone.at/scaled/3233703/v377f9c/full.jpg",
    "isAd": false
  },
  {
    "id": 14,
    "guid": "3234026",
    "title": "„Wäre nicht sinnvoll“ - Heim-EM für WM-Held Mario Götze kein Thema",
    "description": "Für Weltmeister Mario Götze ist die anstehende Europameisterschaft im eigenen Land kein Thema. Der 3...",
    "author": "Krone",
    "date": "2024-01-31 17:32",
    "comments": 15,
    "likes": 131,
    "link": "https://www.krone.at/3234026",
    "image": "https://imgl.krone.at/scaled/2237500/v6b4fd3/full.jpg",
    "isAd": false
  },
  {
    "id": 15,
    "guid": "3234023",
    "title": "krone.tv-News-Show - Mord: Iraner festgenommen++Dominic Thiem im Talk",
    "description": "Nach dem Fund von Leichenteilen am 13. Jänner im Marchfeldkanal in Wien ist nun ein 38-jähriger Iran...",
    "author": "Krone",
    "date": "2024-01-31 17:30",
    "comments": 2,
    "likes": 32,
    "link": "https://www.krone.at/3234023",
    "image": "https://imgl.krone.at/scaled/3234022/vc15f77/full.jpg",
    "isAd": false
  },
  {
    "id": 16,
    "guid": "3234025",
    "title": "Laboriert an Infekt   - Bitter! Zverev muss krank für Davis Cup absagen",
    "description": "Schon wieder fehlt die Nummer 1: Deutschlands Tennis-Herren müssen die Qualifikation für die Davis-C...",
    "author": "Krone",
    "date": "2024-01-31 17:20",
    "comments": 5,
    "likes": 43,
    "link": "https://www.krone.at/3234025",
    "image": "https://imgl.krone.at/scaled/3027739/v34d3a0/full.jpg",
    "isAd": false
  },
  {
    "id": 17,
    "guid": "3234016",
    "title": "„Gesperrte“ Karten - Foto-Registrierung für E-Cards wird erleichtert",
    "description": "Seit 15. Jänner sind E-Cards ohne Passfoto gesperrt. Die Betroffenen - dem Vernehmen nach handelt es...",
    "author": "Krone",
    "date": "2024-01-31 17:19",
    "comments": 21,
    "likes": 145,
    "link": "https://www.krone.at/3234016",
    "image": "https://imgl.krone.at/scaled/2628754/vb1b7fa/full.jpg",
    "isAd": false
  },
  {
    "id": 18,
    "guid": "3234021",
    "title": "Neusiedler See - Rucksack von vermisstem Eisläufer entdeckt",
    "description": "Mitte Jänner verschwand ein Mann, der vermutlich am Neusiedler See eislaufen gegangen war, spurlos. ...",
    "author": "Krone",
    "date": "2024-01-31 17:10",
    "comments": 1,
    "likes": 8,
    "link": "https://www.krone.at/3234021",
    "image": "https://imgl.krone.at/scaled/3219593/vd4a3fe/full.jpg",
    "isAd": false
  },
  {
    "id": 19,
    "guid": "3233922",
    "title": "Landtagssitzung - Stromvertrag-Wechsel: „Kein Zirkus wie in Tirol“",
    "description": "Die Änderung des Elektrizitätswirtschaftsgesetzes für Vorarlberg soll gewährleisten, dass die Kunden...",
    "author": "Krone",
    "date": "2024-01-31 17:05",
    "comments": 9,
    "likes": 58,
    "link": "https://www.krone.at/3233922",
    "image": "https://imgl.krone.at/scaled/2895593/v81e2fb/full.jpg",
    "isAd": false
  },
  {
    "id": 20,
    "guid": "3233876",
    "title": "Schwierige Zeiten - Salzburgs Industrie kämpft mit sinkenden Erträgen",
    "description": "Das letzte Quartal 2023 zeigt das Bild einer Rezession. Auch die Aussichten auf die kommenden Monate...",
    "author": "Krone",
    "date": "2024-01-31 17:00",
    "comments": 5,
    "likes": 30,
    "link": "https://www.krone.at/3233876",
    "image": "https://imgl.krone.at/scaled/3233877/v63cc6a/full.jpg",
    "isAd": false
  },
  {
    "id": 21,
    "guid": "3233431",
    "title": "Kitzbühel - „Krone“-Weltcup-Haus zog hochkarätige Gäste an",
    "description": "Seit zahlreichen Jahren ist die „Kronen Zeitung“ beim Hanhnenkamm-Rennen in Kitzbühel mit dem „Krone...",
    "author": "Krone",
    "date": "2024-01-31 17:00",
    "comments": 12,
    "likes": 112,
    "link": "https://www.krone.at/3233431",
    "image": "https://imgl.krone.at/scaled/3233452/v191fde/full.jpg",
    "isAd": false
  },
  {
    "id": 22,
    "guid": "3233889",
    "title": "Damals völlig neu - Erster Notfallsani rettete vor 50 Jahren Arbeiter",
    "description": "Kurt Radler-Wöss lenkte den ersten Notarztwagen Österreichs. Das Konzept des „Notfallsanitäters“ war...",
    "author": "Krone",
    "date": "2024-01-31 17:28",
    "comments": 2,
    "likes": 189,
    "link": "https://www.krone.at/3233889",
    "image": "https://imgl.krone.at/scaled/3233898/v1bc46f/full.jpg",
    "isAd": false
  },
  {
    "id": 23,
    "guid": "3233509",
    "title": "„Dumme Sachen gemacht“ - Linda Evangelista bereut missglückte Schönheits-OP",
    "description": "Das frühere Supermodel Linda Evangelista bedauert ihren Entschluss zu riskanten Schönheitsoperatione...",
    "author": "Krone",
    "date": "2024-01-31 17:00",
    "comments": 5,
    "likes": 96,
    "link": "https://www.krone.at/3233509",
    "image": "https://imgl.krone.at/scaled/3233538/v18dec3/full.jpg",
    "isAd": false
  },
  {
    "id": 24,
    "guid": "3233977",
    "title": "Rapid-Oranje Kongolo:  - „Ihr habt noch nicht das Beste von mir gesehen!“",
    "description": "Rapids Holländer Nana Kasanwirjo und Terrence Kongolo werten Herbst kritisch, nun wollen sie angreif...",
    "author": "Krone",
    "date": "2024-01-31 16:58",
    "comments": 21,
    "likes": 125,
    "link": "https://www.krone.at/3233977",
    "image": "https://imgl.krone.at/scaled/3233997/v6fc343/full",
    "isAd": false
  },
  {
    "id": 25,
    "guid": "3233992",
    "title": "Öko-Flächenbrand - Bodenfraß: Österreich, Land der verbauten Äcker",
    "description": "Der rasante Bodenfraß wächst sich immer mehr zum ökologischen Flächenbrand aus. Denn die Verbauung e...",
    "author": "Krone",
    "date": "2024-01-31 16:55",
    "comments": 17,
    "likes": 91,
    "link": "https://www.krone.at/3233992",
    "image": "https://imgl.krone.at/scaled/3234001/v3b61e0/full.jpg",
    "isAd": false
  },
  {
    "id": 26,
    "guid": "3233910",
    "title": "Erste Europa-Station - Altach verstärkt sich mit Hungaro-Kanadierin",
    "description": "Die Damen der SPG Altach/Vorderland bekommen Zuwachs. Die 23-jährige Brigitta Pulins - die zuletzt b...",
    "author": "Krone",
    "date": "2024-01-31 16:35",
    "comments": 1,
    "likes": 28,
    "link": "https://www.krone.at/3233910",
    "image": "https://imgl.krone.at/scaled/3233932/vf4cdbc/full.jpg",
    "isAd": false
  },
  {
    "id": 27,
    "guid": "3233967",
    "title": "Steigen Preise wieder? - Sorge um Gasversorgung: Ausbauprojekte stocken",
    "description": "Die Sorge um die Versorgung Österreichs mit Erdgas wächst: Denn die\nLieferungen aus Russland sind ge...",
    "author": "Krone",
    "date": "2024-01-31 16:31",
    "comments": 2,
    "likes": 118,
    "link": "https://www.krone.at/3233967",
    "image": "https://imgl.krone.at/scaled/3233969/va393b4/full.jpg",
    "isAd": false
  },
  {
    "id": 28,
    "guid": "3233864",
    "title": "Freude in Veitsch - Steirerin gewinnt das Jahr Ihres Lebens",
    "description": "Christina, eine junge Krankenschwester aus Veitsch in der Steiermark, erlebte einen unvergesslichen ...",
    "author": "Krone",
    "date": "2024-01-31 16:30",
    "comments": 16,
    "likes": 109,
    "link": "https://www.krone.at/3233864",
    "image": "https://imgl.krone.at/scaled/3201490/v62c529/full.jpg",
    "isAd": false
  },
  {
    "id": 29,
    "guid": "3233907",
    "title": "Wärmepumpe in Betrieb - Rechenzentrum heizt jetzt Klinik Floridsdorf ein",
    "description": "Spitäler sind Energiefresser - durch eine neue Wärmepumpe spart die Klinik Nord ab sofort bis zu zwe...",
    "author": "Krone",
    "date": "2024-01-31 16:30",
    "comments": 9,
    "likes": 125,
    "link": "https://www.krone.at/3233907",
    "image": "https://imgl.krone.at/scaled/3233964/vf35ca1/full.jpg",
    "isAd": false
  },
  {
    "id": 30,
    "guid": "3233941",
    "title": "Reiterer & Neugebauer: - „Taylor Swift ist ein absoluter Glücksfall“",
    "description": "Das Super-Bowl-Fieber steigt. Zur Einstimmung schauten Alfred Neugebauer, der Organisator der Super-...",
    "author": "Krone",
    "date": "2024-01-31 16:18",
    "comments": 9,
    "likes": 48,
    "link": "https://www.krone.at/3233941",
    "image": "https://imgl.krone.at/scaled/3233954/v92975e/full.jpg",
    "isAd": false
  },
  {
    "id": 31,
    "guid": "3233818",
    "title": "Italiens Vizepremier: - Transit-Klage gegen Österreich „in wenigen Tagen“ ",
    "description": "Italiens Verkehrsminister und Vizepremier Matteo Salvini (Lega) hat am Mittwoch die Absicht der ital...",
    "author": "Krone",
    "date": "2024-01-31 16:16",
    "comments": 1,
    "likes": 46,
    "link": "https://www.krone.at/3233818",
    "image": "https://imgl.krone.at/scaled/3233828/v82349c/full.jpg",
    "isAd": false
  },
  {
    "id": 32,
    "guid": "3233633",
    "title": "Gut vorbereitet - Flughafen Wien: „Keine Angst vor Klimaklebern“",
    "description": "Flughafen-Wien-Vorstand Julian Jäger blickt im krone.tv-Interview zufrieden auf das letzte Jahr zurü...",
    "author": "Krone",
    "date": "2024-01-31 16:18",
    "comments": 1,
    "likes": 1,
    "link": "https://www.krone.at/3233633",
    "image": "https://imgl.krone.at/scaled/3233639/v0b2220/full",
    "isAd": false
  },
  {
    "id": 33,
    "guid": "3233790",
    "title": "Betrunken am Bahnhof - Mit Messer auf Security-Mitarbeiter losgegangen",
    "description": "Ein Betrunkener wollte am Bahnhof Dornbirn (Vorarlberg) mit einem gezückten Messer Securitybeamte „v...",
    "author": "Krone",
    "date": "2024-01-31 16:12",
    "comments": 3,
    "likes": 143,
    "link": "https://www.krone.at/3233790",
    "image": "https://imgl.krone.at/scaled/3233789/ve1d192/full.jpg",
    "isAd": false
  },
  {
    "id": 34,
    "guid": "3232841",
    "title": "„Habe Fehler gemacht“ - Eisbäder! So stählt sich Klagenfurt-Ass Gemicibasi",
    "description": "Austria Klagenfurts Turgay Gemicibasi steht im Kroatien-Camp schon um 7 Uhr im Meer, badet auch dahe...",
    "author": "Krone",
    "date": "2024-01-31 16:02",
    "comments": 4,
    "likes": 152,
    "link": "https://www.krone.at/3232841",
    "image": "https://imgl.krone.at/scaled/3233142/v3a96ed/full.jpg",
    "isAd": false
  },
  {
    "id": 35,
    "guid": "3195471",
    "title": "Jahreszeiten im Blick - „Krone“-Fotograf rückt den Kamp ins rechte Licht",
    "description": "Der Film „Kleinod Kamptal“ dokumentiert den Kamp während der vier Jahreszeiten in Niederösterreich -...",
    "author": "Krone",
    "date": "2024-01-31 16:00",
    "comments": 14,
    "likes": 154,
    "link": "https://www.krone.at/3195471",
    "image": "https://imgl.krone.at/scaled/3195474/vf7042a/full.jpg",
    "isAd": false
  },
  {
    "id": 36,
    "guid": "3232991",
    "title": "Felix Großschartner - „Ich habe mich in eine blöde Position gebracht!“",
    "description": "Der Oberösterreicher Felix Großschartner sprach vor seinem Saisonstart am Mittwoch in Spanien über R...",
    "author": "Krone",
    "date": "2024-01-31 16:00",
    "comments": 3,
    "likes": 53,
    "link": "https://www.krone.at/3232991",
    "image": "https://imgl.krone.at/scaled/3232992/va25341/full",
    "isAd": false
  },
  {
    "id": 37,
    "guid": "3233566",
    "title": "Forum - Was darf Kunst?",
    "description": "Kunst hat viele Zwecke - einige Kunstwerke sind schön anzusehen, andere erregen die Gemüter. In den ...",
    "author": "Krone",
    "date": "2024-01-31 16:00",
    "comments": 9,
    "likes": 106,
    "link": "https://www.krone.at/3233566",
    "image": "https://imgl.krone.at/scaled/2058116/vd0c11f/full.jpg",
    "isAd": false
  },
  {
    "id": 38,
    "guid": "3233862",
    "title": "Nächste Krise droht - Kosovarische Regierung verbietet serbischen Dinar",
    "description": "Gerade erst haben Serbien und das Kosovo ihren jahrelangen erbitterten Streit um Autokennzeichen bei...",
    "author": "Krone",
    "date": "2024-01-31 16:00",
    "comments": 1,
    "likes": 6,
    "link": "https://www.krone.at/3233862",
    "image": "https://imgl.krone.at/scaled/3233897/v587fdc/full.jpg",
    "isAd": false
  },
  {
    "id": 39,
    "guid": "3233798",
    "title": "Freeski-Weltcup in USA - Svancer zurück, dafür fällt Müllauer aus",
    "description": "Bei den X-Games musste Freeskier Matej Svancer wegen einer Lebensmittelvergiftung passen. Nun befind...",
    "author": "Krone",
    "date": "2024-01-31 16:00",
    "comments": 25,
    "likes": 158,
    "link": "https://www.krone.at/3233798",
    "image": "https://imgl.krone.at/scaled/2861025/v0604fc/full.jpg",
    "isAd": false
  },
  {
    "id": 40,
    "guid": "3232886",
    "title": "Teil von Initiative - Nationalpark Hohe Tauern will Bewusstsein stärken",
    "description": "Als Mitglied einer internationalen Initiative will man sportliche Aktivitäten und den Naturschutz ve...",
    "author": "Krone",
    "date": "2024-01-31 16:00",
    "comments": 14,
    "likes": 112,
    "link": "https://www.krone.at/3232886",
    "image": "https://imgl.krone.at/scaled/3232888/ve1bb31/full.jpg",
    "isAd": false
  },
  {
    "id": 41,
    "guid": "3233351",
    "title": "Sie sucht neue Liebe - Teri Hatcher wurde bei Hinge „rausgeschmissen“",
    "description": "„Desperate Housewives“-Star Teri Hatcher suchte die Liebe mithilfe von Dating-Apps. Dabei wurde ihr ...",
    "author": "Krone",
    "date": "2024-01-31 16:00",
    "comments": 8,
    "likes": 55,
    "link": "https://www.krone.at/3233351",
    "image": "https://imgl.krone.at/scaled/2060151/v0b21ab/full.jpg",
    "isAd": false
  },
  {
    "id": 42,
    "guid": "3233909",
    "title": "Autark bis 2030 - Mit Riesenschritten in Richtung Energieneutralität",
    "description": "Ein Speichervolumen von 300 Megawattstunden soll das Burgenland bis 2030 zum Selbstversorger mit hei...",
    "author": "Krone",
    "date": "2024-01-31 16:00",
    "comments": 1,
    "likes": 14,
    "link": "https://www.krone.at/3233909",
    "image": "https://imgl.krone.at/scaled/3233923/vde02bf/full.jpg",
    "isAd": false
  },
  {
    "id": 43,
    "guid": "3233702",
    "title": "Psychiaterin erklärt: - „Zerstückelungen haben meist pragmatische Gründe“",
    "description": "Die erfahrene Gerichtspsychiaterin Sigrun Roßmanith erklärt in der „Krone“, warum Mörder an ihren Op...",
    "author": "Krone",
    "date": "2024-01-31 16:12",
    "comments": 2,
    "likes": 35,
    "link": "https://www.krone.at/3233702",
    "image": "https://imgl.krone.at/scaled/3219186/vf0c95a/full.jpg",
    "isAd": false
  },
  {
    "id": 44,
    "guid": "3233908",
    "title": "Teure Geräte gestohlen - GPS-Daten überführte Gastro-Diebe aus Tschechien",
    "description": "Gastronomiegeräte im Wert von 60.000 Euro erbeuteten Diebe im November bei einer Veranstaltung in Sa...",
    "author": "Krone",
    "date": "2024-01-31 16:04",
    "comments": 9,
    "likes": 71,
    "link": "https://www.krone.at/3233908",
    "image": "https://imgl.krone.at/scaled/3216981/v7bc563/full.jpg",
    "isAd": false
  },
  {
    "id": 45,
    "guid": "3233765",
    "title": "Demenzerkrankung - Demi Moore über Bruce Willis: „Man muss loslassen“",
    "description": "Schauspielerin Demi Moore hat über die Demenzerkrankung ihres Ex-Ehemannes Bruce Willis gesprochen. ...",
    "author": "Krone",
    "date": "2024-01-31 15:50",
    "comments": 12,
    "likes": 153,
    "link": "https://www.krone.at/3233765",
    "image": "https://imgl.krone.at/scaled/3233800/ve683ef/full.jpg",
    "isAd": false
  },
  {
    "id": 46,
    "guid": "3233848",
    "title": "Nahe der Staatsgrenze - Dichtung kaputt: Unruhe nach Defekt im AKW Temelín",
    "description": "Besorgniserregende Nachrichten aus dem AKW Temelín nahe der Grenze zu Österreich: Der Kühlkreislauf ...",
    "author": "Krone",
    "date": "2024-01-31 16:48",
    "comments": 12,
    "likes": 119,
    "link": "https://www.krone.at/3233848",
    "image": "https://imgl.krone.at/scaled/1769090/vf63850/full.jpg",
    "isAd": false
  },
  {
    "id": 47,
    "guid": "3232314",
    "title": "Rezept der Woche - Die geschmorte Knolle mit viel Geschmack",
    "description": "Gemüse kann auch ganz viel Geschmack haben. Chefkoch Peter Lehner ist einer der besten Veggie-Köche ...",
    "author": "Krone",
    "date": "2024-01-31 15:32",
    "comments": 1,
    "likes": 25,
    "link": "https://www.krone.at/3232314",
    "image": "https://imgl.krone.at/scaled/3232318/v13d99b/full",
    "isAd": false
  },
  {
    "id": 48,
    "guid": "3233696",
    "title": "20 Jahre Bruckner Uni - „Wir haben jedes Jahr 1000 Anmeldungen“",
    "description": "Vor 20 Jahren wurde das Linzer Bruckner-Konservatorium erfolgreich in die Anton Bruckner Privatunive...",
    "author": "Krone",
    "date": "2024-01-31 15:30",
    "comments": 16,
    "likes": 153,
    "link": "https://www.krone.at/3233696",
    "image": "https://imgl.krone.at/scaled/3233686/v074f09/full.jpg",
    "isAd": false
  },
  {
    "id": 49,
    "guid": "3233729",
    "title": "Menschlich enttäuscht - Cora Schumacher warf Begleiter Jörg aus dem Hotel",
    "description": "Drei Tage hielt es Cora Schumacher im Camp aus, bevor sie es freiwillig verließ. Seitdem wurde es ab...",
    "author": "Krone",
    "date": "2024-01-31 15:18",
    "comments": 3,
    "likes": 117,
    "link": "https://www.krone.at/3233729",
    "image": "https://imgl.krone.at/scaled/3233791/v863a6b/full",
    "isAd": false
  },
  {
    "id": 50,
    "guid": "3233782",
    "title": "Wegen Formalfehlers - Naturschutzbund will Luft-100er auf A10 zurück",
    "description": "Die im vergangenen November erfolgte Aufhebung des zeitweisen „Luft-100ers“ auf der Tauernautobahn z...",
    "author": "Krone",
    "date": "2024-01-31 15:15",
    "comments": 1,
    "likes": 16,
    "link": "https://www.krone.at/3233782",
    "image": "https://imgl.krone.at/scaled/3105513/v176b14/full.jpg",
    "isAd": false
  },
  {
    "id": 51,
    "guid": "3233764",
    "title": "Reformpläne gestoppt - Thailand bleibt bei Majestätsbeleidigung hart",
    "description": "Das thailändische Verfassungsgericht hat Pläne der oppositionellen Fortschrittspartei für eine Refor...",
    "author": "Krone",
    "date": "2024-01-31 15:04",
    "comments": 1,
    "likes": 19,
    "link": "https://www.krone.at/3233764",
    "image": "https://imgl.krone.at/scaled/3233781/v9c6f64/full.jpg",
    "isAd": false
  },
  {
    "id": 52,
    "guid": "3233705",
    "title": "ERSTMALS NUR ZUSEHER - „Ich werde schreien, schimpfen und viel jubeln“",
    "description": "Wenn Österreichs Hallenhockey-Herren am Donnerstag mit dem Gruppenspiel gegen Kroatien in die EM im ...",
    "author": "Krone",
    "date": "2024-01-31 15:03",
    "comments": 1,
    "likes": 16,
    "link": "https://www.krone.at/3233705",
    "image": "https://imgl.krone.at/scaled/2791328/v834604/full.jpg",
    "isAd": false
  },
  {
    "id": 53,
    "guid": "3233772",
    "title": "Fahndung in Innsbruck - Vermummte demolierten Videokameras im Rapoldipark",
    "description": "Unbekannte Vandalen trieben in der Nacht auf Mittwoch im Innsbrucker Rapoldipark ihr Unwesen. Die ve...",
    "author": "Krone",
    "date": "2024-01-31 15:02",
    "comments": 1,
    "likes": 5,
    "link": "https://www.krone.at/3233772",
    "image": "https://imgl.krone.at/scaled/720712/v80a8a8/full.jpg",
    "isAd": false
  },
  {
    "id": 54,
    "guid": "3233467",
    "title": "Giorgi Instagram-Nr.-1 - So heiß sind die Tennis-Stars des Linz-Turniers!",
    "description": "Bis Sonntag zeigen viele der weltbesten Tennis-Spielerinnen beim Upper Austria Ladies am Court im De...",
    "author": "Krone",
    "date": "2024-01-31 15:21",
    "comments": 4,
    "likes": 38,
    "link": "https://www.krone.at/3233467",
    "image": "https://imgl.krone.at/scaled/3233469/v50229a/full.jpg",
    "isAd": false
  },
  {
    "id": 55,
    "guid": "3233732",
    "title": "Hatte Streit im Gehege - Affe ist seit drei Tagen in Schottland auf Flucht",
    "description": "Weil er offenbar Streit mit seinen Kameraden im Gehege hatte, ist ein Affe aus einem schottischen Zo...",
    "author": "Krone",
    "date": "2024-01-31 15:18",
    "comments": 10,
    "likes": 144,
    "link": "https://www.krone.at/3233732",
    "image": "https://imgl.krone.at/scaled/3233750/v91baf2/full.jpg",
    "isAd": false
  },
  {
    "id": 56,
    "guid": "3233761",
    "title": "Trainingsschreck - Knie verletzt! Früchtl hat „Glück im Unglück“",
    "description": "Austria-Goalie Christian Früchtl fällt mit Knieverletzung Wochen aus. Violett ist am Freitag im Cup ...",
    "author": "Krone",
    "date": "2024-01-31 14:49",
    "comments": 17,
    "likes": 104,
    "link": "https://www.krone.at/3233761",
    "image": "https://imgl.krone.at/scaled/3233773/vf4ccab/full.jpg",
    "isAd": false
  },
  {
    "id": 57,
    "guid": "3233660",
    "title": "Entrup-Poker - Absage! Hartberg sagt Nein zu Millionendeal",
    "description": "Das Testspiel von Bundesligist Hartberg im Camp in Catez (Slo) gegen NK Bravo war am Mittwoch eigent...",
    "author": "Krone",
    "date": "2024-01-31 14:52",
    "comments": 11,
    "likes": 104,
    "link": "https://www.krone.at/3233660",
    "image": "https://imgl.krone.at/scaled/3067188/v6dd88b/full.jpg",
    "isAd": false
  },
  {
    "id": 58,
    "guid": "3233730",
    "title": "Pikante Enthüllungen - Heidi Klum: „Leni fand meinen Sex-Schrank“",
    "description": "Schlüpfrige Enthüllungen hat es beim US-Podcast „Call Her Daddy“ von Heidi und Leni Klum gegeben. Da...",
    "author": "Krone",
    "date": "2024-01-31 14:42",
    "comments": 17,
    "likes": 195,
    "link": "https://www.krone.at/3233730",
    "image": "https://imgl.krone.at/scaled/3233731/vec8c96/full.jpg",
    "isAd": false
  },
  {
    "id": 59,
    "guid": "3231646",
    "title": "Tierecke-Interview - Blutspende: So wird Ihr Haustier zum Lebensretter",
    "description": "Genau wie Menschen können auch Tiere auf eine Bluttransfusion angewiesen sein. Die wenigsten Tierhal...",
    "author": "Krone",
    "date": "2024-01-31 14:26",
    "comments": 6,
    "likes": 72,
    "link": "https://www.krone.at/3231646",
    "image": "https://imgl.krone.at/scaled/3232048/v272151/full.jpg",
    "isAd": false
  },
  {
    "id": 60,
    "guid": "3233684",
    "title": "„Herz ist gebrochen“ - „Beach Boy“ Brian Wilson trauert um Frau Melinda",
    "description": "Die Frau von „Beach Boy“ Brian Wilson, Melinda Ledbetter, ist tot. „Mein Herz ist gebrochen“, schrie...",
    "author": "Krone",
    "date": "2024-01-31 15:10",
    "comments": 4,
    "likes": 49,
    "link": "https://www.krone.at/3233684",
    "image": "https://imgl.krone.at/scaled/3233723/vc72d62/full.jpg",
    "isAd": false
  },
  {
    "id": 61,
    "guid": "3233645",
    "title": "Krieg in der Ukraine - Deutschland will weitere 10.000 Soldaten ausbilden",
    "description": "In Deutschland wurden bereits rund 10.000 ukrainische Soldaten für den Krieg gegen Russland ausgebil...",
    "author": "Krone",
    "date": "2024-01-31 14:09",
    "comments": 3,
    "likes": 86,
    "link": "https://www.krone.at/3233645",
    "image": "https://imgl.krone.at/scaled/3233650/v0f9373/full.jpg",
    "isAd": false
  },
  {
    "id": 62,
    "guid": "3233692",
    "title": "WKÖ prgnostiziert: - Wohnungspreise werden ab 2025 deutlich steigen",
    "description": "Keine Entspannung an der Preisfront für frei finanzierte Neubauwohnungen ortet die Wirtschaftskammer...",
    "author": "Krone",
    "date": "2024-01-31 14:14",
    "comments": 3,
    "likes": 104,
    "link": "https://www.krone.at/3233692",
    "image": "https://imgl.krone.at/scaled/873266/v7bdeb0/full.jpg",
    "isAd": false
  },
  {
    "id": 63,
    "guid": "3233648",
    "title": "Im Jahr 2023 - Schlotterer mit sattem Umsatz-Minus",
    "description": "Der Sonnenschutz-Hersteller Schlotterer mit Sitz in Adnet (Tennengau) hat 2023 nach acht Jahren Wach...",
    "author": "Krone",
    "date": "2024-01-31 14:00",
    "comments": 22,
    "likes": 118,
    "link": "https://www.krone.at/3233648",
    "image": "https://imgl.krone.at/scaled/2739751/vfebfc2/full.jpg",
    "isAd": false
  },
  {
    "id": 64,
    "guid": "3231493",
    "title": "Wandel in Möbelbranche - Hersteller und Kunden wollen besser schlafen",
    "description": "Wie gelingt es, den Abfall zu reduzieren? Was kann nach der ursprünglichen Nutzung sogar wiederverwe...",
    "author": "Krone",
    "date": "2024-01-31 14:00",
    "comments": 25,
    "likes": 150,
    "link": "https://www.krone.at/3231493",
    "image": "https://imgl.krone.at/scaled/3231491/v7fdf22/full.jpg",
    "isAd": false
  },
  {
    "id": 65,
    "guid": "3233543",
    "title": "„Made In Austria“ - Hip-Hop-Sampler vereint österreichische Talente",
    "description": "Die Rapperin Beccy-K hat eine Vielzahl an heimischen Rappern und Hip-Hop-Produzenten versammelt, um ...",
    "author": "Krone",
    "date": "2024-01-31 14:00",
    "comments": 9,
    "likes": 72,
    "link": "https://www.krone.at/3233543",
    "image": "https://imgl.krone.at/scaled/3233560/v464e1d/full.jpg",
    "isAd": false
  },
  {
    "id": 66,
    "guid": "3233492",
    "title": "Spielte in Russland - Neuer Stürmer für Austria Klagenfurt",
    "description": "Austria Klagenfurt langt laut „Krone“-Informationen wieder am Transfermarkt zu. Wie man im Winter-Ca...",
    "author": "Krone",
    "date": "2024-01-31 13:59",
    "comments": 7,
    "likes": 137,
    "link": "https://www.krone.at/3233492",
    "image": "https://imgl.krone.at/scaled/3233497/ve79b99/full.jpg",
    "isAd": false
  },
  {
    "id": 67,
    "guid": "3233694",
    "title": "Sichtung in Bludenz - Vorarlberg gibt jetzt Wolf zum Abschuss frei",
    "description": "Nachdem in der Nacht ein Wolf im Siedlungsgebiet von Bludenz (Vorarlberg) gefilmt worden war, reagie...",
    "author": "Krone",
    "date": "2024-01-31 14:07",
    "comments": 5,
    "likes": 177,
    "link": "https://www.krone.at/3233694",
    "image": "https://imgl.krone.at/scaled/2475098/vbf4a5d/full.jpg",
    "isAd": false
  },
  {
    "id": 68,
    "guid": "3233451",
    "title": "nach furchtbarer zeit - Aida Loos: Benefiz-Erfolg für Kinderkrebsforschung",
    "description": "Aida Loos hat die wohl schlimmste Angst einer Mutter erlebt: Bei ihrem Kind wurde ein Tumor entdeckt...",
    "author": "Krone",
    "date": "2024-01-31 17:11",
    "comments": 21,
    "likes": 142,
    "link": "https://www.krone.at/3233451",
    "image": "https://imgl.krone.at/scaled/3233514/v14eb37/full",
    "isAd": false
  },
  {
    "id": 69,
    "guid": "3233655",
    "title": "Prozess in Graz - Nach Streit um Geld: Aus Rache Haus angezündet",
    "description": "Weil er für eine Arbeit seiner Meinung nach zu wenig bezahlt bekommen hatte, hat ein 33-Jähriger die...",
    "author": "Krone",
    "date": "2024-01-31 15:03",
    "comments": 9,
    "likes": 135,
    "link": "https://www.krone.at/3233655",
    "image": "https://imgl.krone.at/scaled/3233693/vc0a13a/full.jpg",
    "isAd": false
  },
  {
    "id": 70,
    "guid": "3233559",
    "title": "Nach Kate & Charles - „Quälende Schmerzen“: Camilla-Nichte wird operiert",
    "description": "Erneut gibt es in Königin Camillas Familie gesundheitliche Sorgen. Nach Prinzessin Kate und König Ch...",
    "author": "Krone",
    "date": "2024-01-31 13:42",
    "comments": 1,
    "likes": 43,
    "link": "https://www.krone.at/3233559",
    "image": "https://imgl.krone.at/scaled/3233599/vccfabe/full.jpg",
    "isAd": false
  },
  {
    "id": 71,
    "guid": "3233665",
    "title": "Nottingham ruft - Dortmunder Reyna wechselt auf die Insel",
    "description": "Borussia Dortmund gibt seinen US-Profi Giovanni Reyna unmittelbar vor der Schließung des Transferfen...",
    "author": "Krone",
    "date": "2024-01-31 13:39",
    "comments": 19,
    "likes": 112,
    "link": "https://www.krone.at/3233665",
    "image": "https://imgl.krone.at/scaled/3233664/v8e4a6b/full.jpg",
    "isAd": false
  },
  {
    "id": 72,
    "guid": "3233652",
    "title": "Mit sofortiger Wirkung - Martin Selmayr hört als EU-Botschafter in Wien auf",
    "description": "Martin Selmayr wechselt den Job und hört als EU-Botschafter in Wien auf. Der gebürtige Deutsche leit...",
    "author": "Krone",
    "date": "2024-01-31 13:33",
    "comments": 19,
    "likes": 185,
    "link": "https://www.krone.at/3233652",
    "image": "https://imgl.krone.at/scaled/3233662/v64a1a1/full.jpg",
    "isAd": false
  },
  {
    "id": 73,
    "guid": "3199199",
    "title": "Grosser Portal-Check - Hotels: So holen Sie das Beste aus Treueprogrammen",
    "description": "Mit einem Ein-Euro-Trick bei Booking.com Genius Level 3 herausholen, ein nicht mehr stornierbares Zi...",
    "author": "Krone",
    "date": "2024-01-31 13:56",
    "comments": 7,
    "likes": 39,
    "link": "https://www.krone.at/3199199",
    "image": "https://imgl.krone.at/scaled/2794338/vbbf4c7/full.jpg",
    "isAd": false
  },
  {
    "id": 74,
    "guid": "3233638",
    "title": "Debütantin ist dabei - Überraschung im WM-Team der Biathleten",
    "description": "Der Österreichische Skiverband hat am Mittwoch sein Team für die Biathlon-Weltmeisterschaften im tsc...",
    "author": "Krone",
    "date": "2024-01-31 13:29",
    "comments": 14,
    "likes": 98,
    "link": "https://www.krone.at/3233638",
    "image": "https://imgl.krone.at/scaled/2931135/v4c6a19/full.jpg",
    "isAd": false
  },
  {
    "id": 75,
    "guid": "3232913",
    "title": "„Ausfragerei“ in Bank - Wer viel Bares einzahlen will, kann Ärger bekommen",
    "description": "Ein Tiroler Pensionist ist entrüstet: Er wurde in einer Bankfiliale in Innsbruck kürzlich „ausgefrag...",
    "author": "Krone",
    "date": "2024-01-31 14:02",
    "comments": 6,
    "likes": 74,
    "link": "https://www.krone.at/3232913",
    "image": "https://imgl.krone.at/scaled/2676007/vae67a4/full.jpg",
    "isAd": false
  },
  {
    "id": 76,
    "guid": "3233535",
    "title": "„Eternal Jugend“ - So sieht Bangles-Sängerin Susanna Hoffs mit 65 aus",
    "description": "Erinnern Sie sich noch an den Hit „Eternal Flame“ von den Bangles - siehe Video oben? Bei Sängerin S...",
    "author": "Krone",
    "date": "2024-01-31 13:19",
    "comments": 8,
    "likes": 194,
    "link": "https://www.krone.at/3233535",
    "image": "https://imgl.krone.at/scaled/3233536/v3d5423/full.jpg",
    "isAd": false
  },
  {
    "id": 77,
    "guid": "3233629",
    "title": "Hard-Abschied - EM-Shootingstar Möstl wechselt nach Deutschland",
    "description": "Die erfolgreiche Handball-EM für Österreichs Nationalteam hat für Tormann-Talent Constantin Möstl gr...",
    "author": "Krone",
    "date": "2024-01-31 13:16",
    "comments": 1,
    "likes": 7,
    "link": "https://www.krone.at/3233629",
    "image": "https://imgl.krone.at/scaled/3230207/v797f33/full.jpg",
    "isAd": false
  },
  {
    "id": 78,
    "guid": "3233345",
    "title": "Neu und hochmodern - LASK trumpft auf: „Kenne ich sonst nur von Milan“",
    "description": "Bilder gibt‘s erst am Wochenende - aber die Schilderungen versprechen viel: Der LASK trumpft mit ein...",
    "author": "Krone",
    "date": "2024-01-31 14:37",
    "comments": 10,
    "likes": 112,
    "link": "https://www.krone.at/3233345",
    "image": "https://imgl.krone.at/scaled/3233575/v4ccf93/full.jpg",
    "isAd": false
  },
  {
    "id": 79,
    "guid": "3233468",
    "title": "Erneute Aktion - Aktivisten benannten Dr.-Karl-Lueger-Platz um",
    "description": "Der Dr.-Karl-Lueger-Platz in der Wiener Innenstadt wurde von Aktivisten in der Nacht zum 27. Jänner ...",
    "author": "Krone",
    "date": "2024-01-31 14:13",
    "comments": 10,
    "likes": 181,
    "link": "https://www.krone.at/3233468",
    "image": "https://imgl.krone.at/scaled/3233522/vebf547/full.jpg",
    "isAd": false
  },
  {
    "id": 80,
    "guid": "3233584",
    "title": "Loipenprojekt geplant - „Ein Langlaufzentrum wäre pure Geldverschwendung“",
    "description": "Seit über zwei Jahren wird in Bad Leonfelden über die Errichtung eines Langlauf- und Biathlonzentrum...",
    "author": "Krone",
    "date": "2024-01-31 13:00",
    "comments": 4,
    "likes": 171,
    "link": "https://www.krone.at/3233584",
    "image": "https://imgl.krone.at/scaled/3233585/v49ef00/full.jpg",
    "isAd": false
  },
  {
    "id": 81,
    "guid": "3233471",
    "title": "Schock für Besitzerin - Zu viel nackte Haut: Werberat verbietet Plakat",
    "description": "Mit einem großflächigen und provokanten Sujet machte Janin Baumann Werbung für ihr Perückengeschäft ...",
    "author": "Krone",
    "date": "2024-01-31 13:09",
    "comments": 1,
    "likes": 1,
    "link": "https://www.krone.at/3233471",
    "image": "https://imgl.krone.at/scaled/3233491/vc4521c/full.jpg",
    "isAd": false
  },
  {
    "id": 82,
    "guid": "3233614",
    "title": "Häftling gefasst - Mit Umbringen bedroht: Polizei gibt Warnschuss ab",
    "description": "Nach einem Freigang am Dienstag kehrte ein Häftling (27) nicht mehr in seine Zelle in Wien-Donaustad...",
    "author": "Krone",
    "date": "2024-01-31 12:56",
    "comments": 3,
    "likes": 20,
    "link": "https://www.krone.at/3233614",
    "image": "https://imgl.krone.at/scaled/2667208/v17b8b8/full.jpg",
    "isAd": false
  },
  {
    "id": 83,
    "guid": "3233608",
    "title": "Seltener Schritt - China meldet Hinrichtungen nach brutalen Morden",
    "description": "In einem seltenen Schritt haben die chinesischen Behörden am Mittwoch die Hinrichtungen in zwei spek...",
    "author": "Krone",
    "date": "2024-01-31 12:52",
    "comments": 1,
    "likes": 40,
    "link": "https://www.krone.at/3233608",
    "image": "https://imgl.krone.at/scaled/1993974/v9e1728/full.jpg",
    "isAd": false
  },
  {
    "id": 84,
    "guid": "3233610",
    "title": "Die Tinte ist trocken: - Fix! Salzburg schnappt sich ÖFB-Zukunftshoffnung",
    "description": "Die Tinte ist trocken: Flavius Daniliuc wechselt vom italienischen Serie-A-Klub US Salernitana 1919 ...",
    "author": "Krone",
    "date": "2024-01-31 12:56",
    "comments": 2,
    "likes": 123,
    "link": "https://www.krone.at/3233610",
    "image": "https://imgl.krone.at/scaled/2979507/v649502/full.jpg",
    "isAd": false
  },
  {
    "id": 85,
    "guid": "3233607",
    "title": "Daniliuc ist da - Salzburg hat einen neuen Verteidiger",
    "description": "Was die „Krone“ bereits berichtet hat, ist nun offiziell. Flavius Daniliuc wechselt von Salernitana ...",
    "author": "Krone",
    "date": "2024-01-31 12:49",
    "comments": 2,
    "likes": 64,
    "link": "https://www.krone.at/3233607",
    "image": "https://imgl.krone.at/scaled/3233606/v1080df/full.jpg",
    "isAd": false
  },
  {
    "id": 86,
    "guid": "3233602",
    "title": "Ex-Freund sah zu - Zwölfjährige auf offener Straße brutal verprügelt",
    "description": "Dienstagabend spielten sich in Wien-Floridsdorf wilde Szenen ab. Eine bislang unbekannte Verdächtige...",
    "author": "Krone",
    "date": "2024-01-31 14:31",
    "comments": 15,
    "likes": 119,
    "link": "https://www.krone.at/3233602",
    "image": "https://imgl.krone.at/scaled/2868073/v44c249/full.jpg",
    "isAd": false
  },
  {
    "id": 87,
    "guid": "3233582",
    "title": "Schock nach Inventur - 100 Maschinen von Großbaustelle verschwunden",
    "description": "Auf einer Baustelle des landeseigenen Tiroler Energieversorgers Tiwag ist es in den vergangenen drei...",
    "author": "Krone",
    "date": "2024-01-31 14:34",
    "comments": 23,
    "likes": 132,
    "link": "https://www.krone.at/3233582",
    "image": "https://imgl.krone.at/scaled/3233596/va53a99/full.jpg",
    "isAd": false
  },
  {
    "id": 88,
    "guid": "3233597",
    "title": "Teures Papierstück - Messis Servietten-Vertrag kommt unter den Hammer",
    "description": "Beim FC Barcelona dürften am Mittwoch alle Alarmglocken angegangen sein. Die legendäre Serviette, au...",
    "author": "Krone",
    "date": "2024-01-31 12:35",
    "comments": 12,
    "likes": 89,
    "link": "https://www.krone.at/3233597",
    "image": "https://imgl.krone.at/scaled/2207686/vb22c7f/full.jpg",
    "isAd": false
  },
  {
    "id": 89,
    "guid": "3233399",
    "title": "Streben nach Exzellenz - Louis Vuitton holt Saoirse Ronan als Botschafterin",
    "description": "Louis Vuitton macht die vierfach Oscar-nominierte Schauspielerin Saoirse Ronan zur neuesten Botschaf...",
    "author": "Krone",
    "date": "2024-01-31 12:30",
    "comments": 24,
    "likes": 155,
    "link": "https://www.krone.at/3233399",
    "image": "https://imgl.krone.at/scaled/3233412/v0a1864/full.jpg",
    "isAd": false
  },
  {
    "id": 90,
    "guid": "3233576",
    "title": "Droht Mancini das Aus? - „Inakzeptables“ Verhalten von Andi Herzogs Gegner",
    "description": "Während Andi Herzog die Erleichterung anzusehen ist, steht Roberto Mancini heftig in der Kritik. Der...",
    "author": "Krone",
    "date": "2024-01-31 13:30",
    "comments": 8,
    "likes": 58,
    "link": "https://www.krone.at/3233576",
    "image": "https://imgl.krone.at/scaled/3233579/v5f31c7/full.jpg",
    "isAd": false
  },
  {
    "id": 91,
    "guid": "3233505",
    "title": "Wolf in Bludenz: - „Wenn er die Zähne fletscht, wäre es was Anderes“",
    "description": "Nach einer Wolfssichtung mitten im städtischen Siedlungsgebiet von Bludenz (Vorarlberg) beruhigt der...",
    "author": "Krone",
    "date": "2024-01-31 14:01",
    "comments": 1,
    "likes": 5,
    "link": "https://www.krone.at/3233505",
    "image": "https://imgl.krone.at/scaled/3110126/v20aacc/full.jpg",
    "isAd": false
  },
  {
    "id": 92,
    "guid": "3233569",
    "title": "Haakon übernimmt - Norwegischer König Harald erneut im Krankenstand",
    "description": "Der norwegische König Harald V. (86) ist erneut krank. Wegen einer Atemwegsinfektion ist der Monarch...",
    "author": "Krone",
    "date": "2024-01-31 12:09",
    "comments": 14,
    "likes": 78,
    "link": "https://www.krone.at/3233569",
    "image": "https://imgl.krone.at/scaled/3001488/vc9fcfe/full.jpg",
    "isAd": false
  },
  {
    "id": 93,
    "guid": "3233525",
    "title": "Folgenschwerer Crash - Bub (5) tot: YouTuber nach „Challenge“ verurteilt",
    "description": "Ein 20-jähriger italienischer Youtuber, der bei einer Challenge für ein YouTube-Video mit einem Lamb...",
    "author": "Krone",
    "date": "2024-01-31 15:31",
    "comments": 7,
    "likes": 57,
    "link": "https://www.krone.at/3233525",
    "image": "https://imgl.krone.at/scaled/3233561/v0bb006/full.jpg",
    "isAd": false
  },
  {
    "id": 94,
    "guid": "3233446",
    "title": "Auch Fachkräfte fehlen - Kärntner Industrie leidet unter hohen Lohnkosten",
    "description": "Nach Jahren der Krise leiden die heimischen Unternehmen noch immer unter den hohen Kosten. Und das t...",
    "author": "Krone",
    "date": "2024-01-31 12:01",
    "comments": 2,
    "likes": 13,
    "link": "https://www.krone.at/3233446",
    "image": "https://imgl.krone.at/scaled/3135627/v275a78/full.jpg",
    "isAd": false
  },
  {
    "id": 95,
    "guid": "3233510",
    "title": "21 Fälle - TikTok-Video verleitete Burschen zu Betrug",
    "description": "Dank steirischer IT-Ermittler wurden zwei Jugendliche aus Mödling (16, 17) ausgeforscht, die im Inte...",
    "author": "Krone",
    "date": "2024-01-31 14:35",
    "comments": 5,
    "likes": 34,
    "link": "https://www.krone.at/3233510",
    "image": "https://imgl.krone.at/scaled/2942755/v942874/full.jpg",
    "isAd": false
  },
  {
    "id": 96,
    "guid": "3233529",
    "title": "Söhnchen ist da - Süße Papa-Freuden für Eisbullen-Spieler",
    "description": "Während die Eisbullen am Dienstag gegen Fehervar eine Niederlage einstecken mussten, hatte ein Spiel...",
    "author": "Krone",
    "date": "2024-01-31 11:55",
    "comments": 12,
    "likes": 92,
    "link": "https://www.krone.at/3233529",
    "image": "https://imgl.krone.at/scaled/3233531/vafbd94/full",
    "isAd": false
  },
  {
    "id": 97,
    "guid": "3233537",
    "title": "Magnitude von 2,1 - Erdbebenserie im Tiroler Unterland nimmt kein Ende",
    "description": "Die Erdbebenserie im Tiroler Bezirk Kitzbühel hat sich am Mittwoch fortgesetzt. Diesmal lag das Epiz...",
    "author": "Krone",
    "date": "2024-01-31 11:55",
    "comments": 6,
    "likes": 45,
    "link": "https://www.krone.at/3233537",
    "image": "https://imgl.krone.at/scaled/1583559/v9f07e8/full.jpg",
    "isAd": false
  },
  {
    "id": 98,
    "guid": "3233498",
    "title": "Debatte im Nationalrat - Wahlkampfgetöse um ORF und Kickls „Propaganda“",
    "description": "Die FPÖ hat eines ihrer Lieblingsthemen - den ORF - für ihre „Aktuelle Stunde“ im Nationalrat auserk...",
    "author": "Krone",
    "date": "2024-01-31 13:51",
    "comments": 2,
    "likes": 17,
    "link": "https://www.krone.at/3233498",
    "image": "https://imgl.krone.at/scaled/3233501/v4a0b0b/full.jpg",
    "isAd": false
  },
  {
    "id": 99,
    "guid": "3233540",
    "title": "Was machen Spieler? - Klopp: „Vor einer Woche hat niemand gefragt!“",
    "description": "Liverpool-Trainer Jürgen Klopp hat Befürchtungen zu einem Auseinanderfallen des Topklubs nach seinem...",
    "author": "Krone",
    "date": "2024-01-31 11:50",
    "comments": 13,
    "likes": 96,
    "link": "https://www.krone.at/3233540",
    "image": "https://imgl.krone.at/scaled/3202718/v2de0b2/full.jpg",
    "isAd": false
  },
  {
    "id": 100,
    "guid": "3233391",
    "title": "Gold-Vici mit Sturz - ÖSV-Girls krallen sich die nächsten zwei Medaillen",
    "description": "Auch beim zweiten Damen-Rennen der Junioren-WM im französischen Châtel hatte das rot-weiß-rote Team ...",
    "author": "Krone",
    "date": "2024-01-31 13:41",
    "comments": 1,
    "likes": 52,
    "link": "https://www.krone.at/3233391",
    "image": "https://imgl.krone.at/scaled/3233423/v34e832/full.jpg",
    "isAd": false
  },
  {
    "id": 101,
    "guid": "3233533",
    "title": "Keine OP notwendig - Trotz Kreuzbandriss: Blitz-Comeback von Ski-Dame?",
    "description": "Die Schweizerin Joana Hählen könnte trotz eines am vergangenen Wochenende erlittenen Kreuzbandrisses...",
    "author": "Krone",
    "date": "2024-01-31 11:41",
    "comments": 19,
    "likes": 163,
    "link": "https://www.krone.at/3233533",
    "image": "https://imgl.krone.at/scaled/3230418/vb0d3fe/full.jpg",
    "isAd": false
  },
  {
    "id": 102,
    "guid": "3233513",
    "title": "Klub knallhart - Italo-Kicker stiehlt Auto und flüchtet vor Polizei",
    "description": "Der italienische Zweitligist FC Südtirol hat seinen Spieler Amney Moutassime gefeuert. Grund: Er ent...",
    "author": "Krone",
    "date": "2024-01-31 11:41",
    "comments": 16,
    "likes": 129,
    "link": "https://www.krone.at/3233513",
    "image": "https://imgl.krone.at/scaled/3059469/v7f0de3/full.jpg",
    "isAd": false
  },
  {
    "id": 103,
    "guid": "3233453",
    "title": "OGH wies Revision ab - Steibl fix mit Klage gegen Ischgler TVB abgeblitzt",
    "description": "Die arbeitsrechtliche Auseinandersetzung zwischen dem Tourismusverband Ischgl-Paznaun und seinem ehe...",
    "author": "Krone",
    "date": "2024-01-31 11:47",
    "comments": 26,
    "likes": 188,
    "link": "https://www.krone.at/3233453",
    "image": "https://imgl.krone.at/scaled/2142212/vf21622/full.jpg",
    "isAd": false
  },
  {
    "id": 104,
    "guid": "3233459",
    "title": "Klare Wahlanalyse: - Glawischnig: „Duell heißt Nehammer-Babler“",
    "description": "Im aktuellen „Politik-Duell“ auf krone.tv wird auch der Ausgang der kommenden Nationalratswahl disku...",
    "author": "Krone",
    "date": "2024-01-31 11:30",
    "comments": 9,
    "likes": 75,
    "link": "https://www.krone.at/3233459",
    "image": "https://imgl.krone.at/scaled/3233457/vd7411c/full.jpg",
    "isAd": false
  },
  {
    "id": 105,
    "guid": "3233292",
    "title": "Dashcam-Videos - Das sind Großbritanniens schlimmste Autofahrer",
    "description": "Im Rahmen der „Operation Snap“ rief die britische Polizei Bürger dazu auf, Dashcam-Videos von Verkeh...",
    "author": "Krone",
    "date": "2024-01-31 13:11",
    "comments": 18,
    "likes": 128,
    "link": "https://www.krone.at/3233292",
    "image": "https://imgl.krone.at/scaled/3233328/v7333f3/full.jpg",
    "isAd": false
  },
  {
    "id": 106,
    "guid": "3233496",
    "title": "Linz-Weltrekordversuch - Was LASK mit 149 Eigentoren und Kampfjet verbindet",
    "description": "Der LASK will beim Cup-Hit gegen Salzburg mit einer gemeinsamen Reanimationsaktion mit den Fans den ...",
    "author": "Krone",
    "date": "2024-01-31 11:25",
    "comments": 15,
    "likes": 95,
    "link": "https://www.krone.at/3233496",
    "image": "https://imgl.krone.at/scaled/3233493/v6c2b3b/full.jpg",
    "isAd": false
  },
  {
    "id": 107,
    "guid": "3233398",
    "title": "„Skurriles Finale“ - So kam es zu russischen Zeugen im Kurz-Prozess",
    "description": "Zwei russische Geschäftsleute sollen heute im Prozess gegen Ex-Kanzler Sebastian Kurz aussagen und d...",
    "author": "Krone",
    "date": "2024-01-31 17:41",
    "comments": 16,
    "likes": 97,
    "link": "https://www.krone.at/3233398",
    "image": "https://imgl.krone.at/scaled/3191664/v426d59/full.jpg",
    "isAd": false
  },
  {
    "id": 108,
    "guid": "3233435",
    "title": "Noch lange To-Do-Liste - ÖVP und Grüne wollen bis in den Herbst „hackeln“",
    "description": "Trotz anhaltender Neuwahlgerüchte haben die Regierungsparteien einmal mehr beteuert, bis zum Ende de...",
    "author": "Krone",
    "date": "2024-01-31 11:12",
    "comments": 1,
    "likes": 55,
    "link": "https://www.krone.at/3233435",
    "image": "https://imgl.krone.at/scaled/3233437/v3b5ac8/full.jpg",
    "isAd": false
  },
  {
    "id": 109,
    "guid": "3232384",
    "title": "Politbeben Pernersdorf - Kippt „Durchstarter“ den jüngsten Bürgermeister?",
    "description": "Nach der ersten Wahl im heurigen Jahr, jener des Pernersdorfer Gemeinderates, ist kein Stein auf dem...",
    "author": "Krone",
    "date": "2024-01-31 16:48",
    "comments": 9,
    "likes": 161,
    "link": "https://www.krone.at/3232384",
    "image": "https://imgl.krone.at/scaled/3232730/v0fb5f9/full.jpg",
    "isAd": false
  },
  {
    "id": 110,
    "guid": "3233429",
    "title": "„Falsch investiert“ - Dämmstoff-Firma Brucha insolvent: 500 Jobs wackeln",
    "description": "Der Dämmstoffproduzent Brucha mit Sitz in Niederösterreich ist insolvent. Das Unternehmen beschäftig...",
    "author": "Krone",
    "date": "2024-01-31 13:33",
    "comments": 14,
    "likes": 72,
    "link": "https://www.krone.at/3233429",
    "image": "https://imgl.krone.at/scaled/2824503/v524089/full.jpg",
    "isAd": false
  },
  {
    "id": 111,
    "guid": "3233479",
    "title": "Doppelte Tätlichkeit - „Widerlich!“ Große Aufregung um Liverpool-Talent",
    "description": "Luca Furnell-Gill gehört zu den großen Zukunftshoffnungen beim FC Liverpool. Im Spiel gegen die U18-...",
    "author": "Krone",
    "date": "2024-01-31 11:06",
    "comments": 1,
    "likes": 7,
    "link": "https://www.krone.at/3233479",
    "image": "https://imgl.krone.at/scaled/3233483/ve6d265/full.jpg",
    "isAd": false
  },
  {
    "id": 112,
    "guid": "3233445",
    "title": "Bamba-Ersatz gefunden - Neuer WAC-Stürmer auf den Spuren von Yaya Toure",
    "description": "Der WAC hat einen neuen Stürmer! Sankara Karamoko (20) kommt vom amtierenden ivorischen Meister ASEC...",
    "author": "Krone",
    "date": "2024-01-31 11:11",
    "comments": 5,
    "likes": 129,
    "link": "https://www.krone.at/3233445",
    "image": "https://imgl.krone.at/scaled/3233465/v28b09f/full.jpg",
    "isAd": false
  },
  {
    "id": 113,
    "guid": "3233438",
    "title": "Pistencrash - Frau nach Kollision mit Snowboarder verletzt",
    "description": "Erst stürzte eine Snowboarderin im Nobel-Skiort Lech, dann wurde sie noch von einem anderen Wintersp...",
    "author": "Krone",
    "date": "2024-01-31 11:02",
    "comments": 5,
    "likes": 31,
    "link": "https://www.krone.at/3233438",
    "image": "https://imgl.krone.at/scaled/2584843/ve910a5/full.jpg",
    "isAd": false
  },
  {
    "id": 114,
    "guid": "3232787",
    "title": "Kein Erfolg mit Kosovo - Kärntner Ex-Weltmeisterin beendet vorzeitig Saison",
    "description": "Die Gailtaler Ex-Skisprung-Weltmeisterin Sophie Sorschag beendet Zusammenarbeit mit Trainer, reiste ...",
    "author": "Krone",
    "date": "2024-01-31 13:13",
    "comments": 19,
    "likes": 179,
    "link": "https://www.krone.at/3232787",
    "image": "https://imgl.krone.at/scaled/3232795/v6e2bc8/full.jpg",
    "isAd": false
  },
  {
    "id": 115,
    "guid": "3233418",
    "title": "Jan Schlaudraff: - „Können nur warten, was Wolfsburg tut“",
    "description": "St. Pöltens Geschäftsführer Schlaudraff reiste erneut vergeblich nach Wolfsburg, um Klarheit zum The...",
    "author": "Krone",
    "date": "2024-01-31 11:00",
    "comments": 9,
    "likes": 51,
    "link": "https://www.krone.at/3233418",
    "image": "https://imgl.krone.at/scaled/3233419/v823a58/full.jpg",
    "isAd": false
  },
  {
    "id": 116,
    "guid": "3232542",
    "title": "Live in der Sargfabrik - Zelda Weber: Wo sich der Soul seinen Weg bahnt",
    "description": "Mit Zelda Weber gibt es in Österreich seit einiger Zeit wieder eine Künstlerin, die Grandezza und Sc...",
    "author": "Krone",
    "date": "2024-01-31 11:00",
    "comments": 4,
    "likes": 129,
    "link": "https://www.krone.at/3232542",
    "image": "https://imgl.krone.at/scaled/3232557/vcd6faa/full.jpg",
    "isAd": false
  },
  {
    "id": 117,
    "guid": "3232711",
    "title": "In Siegendorf - Standort der Shell-Tankstelle scheint wie verhext!",
    "description": "Sie wurde auf erstklassigen Ackerböden errichtet und sollte eine Goldgrube werden: Die top-moderne S...",
    "author": "Krone",
    "date": "2024-01-31 11:00",
    "comments": 5,
    "likes": 34,
    "link": "https://www.krone.at/3232711",
    "image": "https://imgl.krone.at/scaled/3232759/v9e233c/full.jpg",
    "isAd": false
  },
  {
    "id": 118,
    "guid": "3233342",
    "title": "400 Millionen Euro - Online-Glücksspielerlöse der Mafia beschlagnahmt",
    "description": "Im Rahmen von Ermittlungen gegen die Mafia hat die italienische Justiz Vermögenswerte im Wert von et...",
    "author": "Krone",
    "date": "2024-01-31 10:57",
    "comments": 16,
    "likes": 156,
    "link": "https://www.krone.at/3233342",
    "image": "https://imgl.krone.at/scaled/2743923/v20e5c4/full.jpg",
    "isAd": false
  },
  {
    "id": 119,
    "guid": "3233161",
    "title": "Volkspremium-Limo - VW ID.7: Besser als BMW i5 und Mercedes EQE?",
    "description": "Zugegeben: Die Frage im Titel ist provokant. Und das hier soll auch kein Vergleichstest zwischen dem...",
    "author": "Krone",
    "date": "2024-01-31 10:55",
    "comments": 14,
    "likes": 155,
    "link": "https://www.krone.at/3233161",
    "image": "https://imgl.krone.at/scaled/3233163/v316731/full.jpg",
    "isAd": false
  },
  {
    "id": 120,
    "guid": "3233441",
    "title": "NBA - Knicks beenden Rekord-Jänner mit dem 14. Sieg",
    "description": "Die Basketballer der New York Knicks haben den besten Jahresstart in ihrer NBA-Geschichte hingelegt....",
    "author": "Krone",
    "date": "2024-01-31 10:53",
    "comments": 21,
    "likes": 108,
    "link": "https://www.krone.at/3233441",
    "image": "https://imgl.krone.at/scaled/3233443/v28964a/full.jpg",
    "isAd": false
  },
  {
    "id": 121,
    "guid": "3233430",
    "title": "Maßnahmen eingeleitet - Masernalarm in Tirol: Bisher 2 Fälle im Unterland!",
    "description": "Im Tiroler Bezirk Kufstein geht offenbar das hochansteckende Masern-Virus um. Laut derzeitigem Kennt...",
    "author": "Krone",
    "date": "2024-01-31 11:09",
    "comments": 11,
    "likes": 117,
    "link": "https://www.krone.at/3233430",
    "image": "https://imgl.krone.at/scaled/1904569/v0642db/full.jpg",
    "isAd": false
  },
  {
    "id": 122,
    "guid": "3233353",
    "title": "Mehr HPV-Impfungen - EU-Kommission will Kampf gegen Krebs vorantreiben",
    "description": "Die EU-Kommission macht sich für mehr Impfungen gegen Krebserkrankungen stark. Mehr Menschen sollen ...",
    "author": "Krone",
    "date": "2024-01-31 10:38",
    "comments": 13,
    "likes": 92,
    "link": "https://www.krone.at/3233353",
    "image": "https://imgl.krone.at/scaled/3233358/v4a9886/full.jpg",
    "isAd": false
  },
  {
    "id": 123,
    "guid": "3233223",
    "title": "Bulle Fernando - Ein „Vater Unser“ am Tag für die Sturm-Rakete",
    "description": "Fernando kann und soll für Abomeister Salzburg im Frühjahr ein Unterschiedsspieler sein. Trainer Ger...",
    "author": "Krone",
    "date": "2024-01-31 11:02",
    "comments": 14,
    "likes": 142,
    "link": "https://www.krone.at/3233223",
    "image": "https://imgl.krone.at/scaled/3233225/vd9e966/full.jpg",
    "isAd": false
  },
  {
    "id": 124,
    "guid": "3233321",
    "title": "Ultrawide, DLSS & Co. - „Horizon Forbidden West“: Das kann die PC-Version",
    "description": "Am 21. März bringt Sony seinen PS5-Kracher „Horizon Forbidden West“ auch auf den PC - in einer übera...",
    "author": "Krone",
    "date": "2024-01-31 10:27",
    "comments": 6,
    "likes": 37,
    "link": "https://www.krone.at/3233321",
    "image": "https://imgl.krone.at/scaled/2607526/v3abb14/full.jpg",
    "isAd": false
  },
  {
    "id": 125,
    "guid": "3233357",
    "title": "Großer Frauenanteil  - 2023 war Rekordjahr bei Unternehmensgründungen",
    "description": "Trotz vieler wirtschaftlicher Unsicherheiten ist der Gründergeist in Österreich intakt. 2023 wurden ...",
    "author": "Krone",
    "date": "2024-01-31 10:17",
    "comments": 1,
    "likes": 29,
    "link": "https://www.krone.at/3233357",
    "image": "https://imgl.krone.at/scaled/3233366/v00fbdb/full.jpg",
    "isAd": false
  },
  {
    "id": 126,
    "guid": "3233269",
    "title": "Heißer geht‘s kaum! - Jennifer Lopez rekelt sich im Nippel-BH in Video",
    "description": "Ist das Jennifer Lopez‘ heißester Musikclip aller Zeiten? Die Latina veröffentlichte Anfang der Woch...",
    "author": "Krone",
    "date": "2024-01-31 10:14",
    "comments": 4,
    "likes": 28,
    "link": "https://www.krone.at/3233269",
    "image": "https://imgl.krone.at/scaled/3233315/v20741c/full.jpg",
    "isAd": false
  },
  {
    "id": 127,
    "guid": "3233371",
    "title": "Husten plagt Lamparter - „Das Zuschauen auf der Couch tut mir extrem weh!“",
    "description": "Im Vorjahr erfüllte sich Kombinierer-Jungstar Johannes Lamparter mit dem Sieg beim Nordic-Triple in ...",
    "author": "Krone",
    "date": "2024-01-31 10:18",
    "comments": 1,
    "likes": 76,
    "link": "https://www.krone.at/3233371",
    "image": "https://imgl.krone.at/scaled/3216820/v9c30b7/full.jpg",
    "isAd": false
  },
  {
    "id": 128,
    "guid": "3233352",
    "title": "Will sie „eliminieren“ - Israels Außenminister: „Hamas sind neue Nazis“",
    "description": "Der israelische Außenminister Israel Katz der international geforderten Zweistaatenlösung eine klare...",
    "author": "Krone",
    "date": "2024-01-31 12:10",
    "comments": 5,
    "likes": 41,
    "link": "https://www.krone.at/3233352",
    "image": "https://imgl.krone.at/scaled/3233361/v17509b/full.jpg",
    "isAd": false
  },
  {
    "id": 129,
    "guid": "3233372",
    "title": "Skiunfall in Tirol - Bub kracht in Funpark gegen Zaun - schwer verletzt",
    "description": "Fataler Wintersportunfall am Dienstag im Tiroler Ötztal: Ein sechsjähriger Bub aus der Schweiz krach...",
    "author": "Krone",
    "date": "2024-01-31 10:20",
    "comments": 2,
    "likes": 132,
    "link": "https://www.krone.at/3233372",
    "image": "https://imgl.krone.at/scaled/2048884/vb5dc22/full.jpg",
    "isAd": false
  },
  {
    "id": 130,
    "guid": "3233303",
    "title": "Teenager werden Mütter - Jungpapa Marcell will nach Gefängnis Pornos drehen",
    "description": "Marcell bekommt nach seinem Gefängnisaufenthalt gar nicht genug vom Duft der Freiheit. Mit Gelegenhe...",
    "author": "Krone",
    "date": "2024-01-31 11:35",
    "comments": 31,
    "likes": 189,
    "link": "https://www.krone.at/3233303",
    "image": "https://imgl.krone.at/scaled/3233365/v7248db/full.jpg",
    "isAd": false
  },
  {
    "id": 131,
    "guid": "3233349",
    "title": "Spieler beurlaubt - Frau vergewaltigt? Vorwürfe gegen Weltmeister",
    "description": "Im Skandal um Vergewaltigungsvorwürfe gegen vier NHL-Profis und einen weiteren ehemaligen Spieler de...",
    "author": "Krone",
    "date": "2024-01-31 10:10",
    "comments": 1,
    "likes": 3,
    "link": "https://www.krone.at/3233349",
    "image": "https://imgl.krone.at/scaled/3233379/vf618c4/full.jpg",
    "isAd": false
  },
  {
    "id": 132,
    "guid": "3233288",
    "title": "Keller ausgeräumt - Durstiger Einbrecher bevorzugte vor allem Zweigelt",
    "description": "Kellerabteile und unversperrte Pkw haben es einem 30-jährigen Astener „angetan“. Immer wieder brach ...",
    "author": "Krone",
    "date": "2024-01-31 14:16",
    "comments": 24,
    "likes": 169,
    "link": "https://www.krone.at/3233288",
    "image": "https://imgl.krone.at/scaled/2467605/v1c1ca5/full.jpg",
    "isAd": false
  },
  {
    "id": 133,
    "guid": "3233294",
    "title": "Liebe zu Altach-Lady - Umbruch überraschte Dornbirn-Zugang Umjenovic",
    "description": "Thomas Janeschitz und Eric Orie hatten sich um Stefan Umjenovic bemüht - und schließlich auch zu ein...",
    "author": "Krone",
    "date": "2024-01-31 10:17",
    "comments": 13,
    "likes": 115,
    "link": "https://www.krone.at/3233294",
    "image": "https://imgl.krone.at/scaled/3233347/vf03fa1/full.jpg",
    "isAd": false
  },
  {
    "id": 134,
    "guid": "3233355",
    "title": "Im „Pop-Up-Stadion“ - Superstar Adele gibt vier Konzerte in München",
    "description": "Acht Jahre liegen die letzten Adele-Liveauftritte am europäischen Festland mittlerweile zurück. Das ...",
    "author": "Krone",
    "date": "2024-01-31 09:50",
    "comments": 16,
    "likes": 168,
    "link": "https://www.krone.at/3233355",
    "image": "https://imgl.krone.at/scaled/3037996/v8c3bd6/full.jpg",
    "isAd": false
  },
  {
    "id": 135,
    "guid": "3233302",
    "title": "Treibstoffe billiger - Preise für Haushaltsenergie im Dezember gesunken",
    "description": "Die Preise für Haushaltsenergie sind im Dezember im Monatsvergleich zurückgegangen. Im Jahresverglei...",
    "author": "Krone",
    "date": "2024-01-31 11:31",
    "comments": 4,
    "likes": 54,
    "link": "https://www.krone.at/3233302",
    "image": "https://imgl.krone.at/scaled/2635398/v18a0db/full.jpg",
    "isAd": false
  },
  {
    "id": 136,
    "guid": "3233329",
    "title": "„Viel mehr Hardcore“ - Rhaenyra-Darstellerin Milly Alcock wird Supergirl",
    "description": "„House of the Dragon“-Star Milly Alcock wird das nächste Supergirl. Die 23-jährige Schauspielerin ha...",
    "author": "Krone",
    "date": "2024-01-31 09:43",
    "comments": 4,
    "likes": 104,
    "link": "https://www.krone.at/3233329",
    "image": "https://imgl.krone.at/scaled/3233333/v610bc8/full.jpg",
    "isAd": false
  },
  {
    "id": 137,
    "guid": "3233319",
    "title": "Phänomen Elke Kahr - „9100 Euro? So viel brauche ich ja gar nicht“",
    "description": "Wie kein anderer Grazer Bürgermeister davor sorgt die Kommunistin Elke Kahr auch international für S...",
    "author": "Krone",
    "date": "2024-01-31 11:40",
    "comments": 18,
    "likes": 126,
    "link": "https://www.krone.at/3233319",
    "image": "https://imgl.krone.at/scaled/2989495/ve4064b/full.jpg",
    "isAd": false
  },
  {
    "id": 138,
    "guid": "3232375",
    "title": "Forum - Höhere Bierpreise: Welches Bier ist das Geld wert?",
    "description": "Durchschnittlich 4,75€ kostet ein halber Liter Bier in österreichischen Gasthäusern, in vielen Betri...",
    "author": "Krone",
    "date": "2024-01-31 09:30",
    "comments": 2,
    "likes": 94,
    "link": "https://www.krone.at/3232375",
    "image": "https://imgl.krone.at/scaled/2036704/v060969/full.jpg",
    "isAd": false
  },
  {
    "id": 139,
    "guid": "3233334",
    "title": "Verwaltung betroffen - Linz: Brau Union setzt 50 Mitarbeiter vor die Türe",
    "description": "Die Mitteilung aus der Heineken-Konzernzentrale kam überraschend: Die Brau Union (dazu gehört etwa Z...",
    "author": "Krone",
    "date": "2024-01-31 09:59",
    "comments": 1,
    "likes": 16,
    "link": "https://www.krone.at/3233334",
    "image": "https://imgl.krone.at/scaled/3233338/v0db4c5/full.jpg",
    "isAd": false
  },
  {
    "id": 140,
    "guid": "3233316",
    "title": "Bei Zahlungsstopp - UNO warnt: „Katastrophale“ Folgen im Gazastreifen",
    "description": "Mehrere UN-Organisationen haben vor einem Stopp der Finanzierung des massiv in die Kritik geratenen ...",
    "author": "Krone",
    "date": "2024-01-31 09:27",
    "comments": 10,
    "likes": 132,
    "link": "https://www.krone.at/3233316",
    "image": "https://imgl.krone.at/scaled/3233336/vb794b5/full.jpg",
    "isAd": false
  },
  {
    "id": 141,
    "guid": "3232852",
    "title": "„Aktion scharf“ - Freizeitwohnsitze: Tiroler blechen wie Deutsche",
    "description": "Das Land Tirol setzte auf eine „Aktion scharf“ zur Aufdeckung nicht gemeldeter Freizeitwohnsitze, da...",
    "author": "Krone",
    "date": "2024-01-31 09:22",
    "comments": 6,
    "likes": 48,
    "link": "https://www.krone.at/3232852",
    "image": "https://imgl.krone.at/scaled/3147362/va83567/full.jpg",
    "isAd": false
  },
  {
    "id": 142,
    "guid": "3233304",
    "title": "Tragischer Vorfall - Österreicher in Indien tot aufgefunden",
    "description": "Traurige Nachrichten aus Indien: Ein Österreicher ist am Dienstag in Amritsar verstorben.",
    "author": "Krone",
    "date": "2024-01-31 09:18",
    "comments": 3,
    "likes": 21,
    "link": "https://www.krone.at/3233304",
    "image": "https://imgl.krone.at/scaled/3233323/v004b63/full.jpg",
    "isAd": false
  },
  {
    "id": 143,
    "guid": "3233283",
    "title": "„Läuft wirklich gut“ - US-Star Elisabeth Moss  bestätigt Schwangerschaft",
    "description": "Die US-amerikanische Schauspielerin Elisabeth Moss erwartet mit 41 Jahren ihr erstes Kind. Sie bestä...",
    "author": "Krone",
    "date": "2024-01-31 09:09",
    "comments": 20,
    "likes": 118,
    "link": "https://www.krone.at/3233283",
    "image": "https://imgl.krone.at/scaled/3233284/vb2f4e5/full.jpg",
    "isAd": false
  },
  {
    "id": 144,
    "guid": "3233300",
    "title": "Sollte sexyer wirken - Empörung über retuschiertes Foto von Politikerin",
    "description": "Das bearbeitete Foto einer Politikerin hat einem australischen Nachrichtensender den Vorwurf des Sex...",
    "author": "Krone",
    "date": "2024-01-31 09:09",
    "comments": 2,
    "likes": 13,
    "link": "https://www.krone.at/3233300",
    "image": "https://imgl.krone.at/scaled/3233301/v5dbb0b/full.jpg",
    "isAd": false
  },
  {
    "id": 145,
    "guid": "3233308",
    "title": "Der Deal ist perfekt - Nun wertvollster Profi: Neuer Klub für Holzhauser!",
    "description": "Neue Aufgabe für Raphael Holzhauser: Der ehemalige Austria-Wien-Kapitän unterschreibt beim FC Swift ...",
    "author": "Krone",
    "date": "2024-01-31 09:37",
    "comments": 6,
    "likes": 80,
    "link": "https://www.krone.at/3233308",
    "image": "https://imgl.krone.at/scaled/2247268/vebb200/full.jpg",
    "isAd": false
  },
  {
    "id": 146,
    "guid": "3233287",
    "title": "Künftig neue Regeln - Herkunftsländer von Honig kommen auf Verpackung",
    "description": "Auf den Verpackungen von Honig muss künftig das Herkunftsland deutlich erkennbar angegeben werden. N...",
    "author": "Krone",
    "date": "2024-01-31 10:44",
    "comments": 17,
    "likes": 86,
    "link": "https://www.krone.at/3233287",
    "image": "https://imgl.krone.at/scaled/3233291/va6b050/full.jpg",
    "isAd": false
  },
  {
    "id": 147,
    "guid": "3232468",
    "title": "Sorge ist groß - Nach Pleite: 30 Senioren zittern um ihr Zuhause",
    "description": "Auf den ersten Blick ist es eine der vielen Pleiten des Jahres: Am Landesgericht Linz wurde über den...",
    "author": "Krone",
    "date": "2024-01-31 09:00",
    "comments": 1,
    "likes": 10,
    "link": "https://www.krone.at/3232468",
    "image": "https://imgl.krone.at/scaled/3232437/va2ace3/full.jpg",
    "isAd": false
  },
  {
    "id": 148,
    "guid": "3233282",
    "title": "AK-SERVICE-TIPP - Muss ich Ausbildungskosten zurückzahlen?",
    "description": "Dass auch bei einer einvernehmlichen Auflösung des Dienstvertrages die Refundierung von Ausbildungsk...",
    "author": "Krone",
    "date": "2024-01-31 09:00",
    "comments": 3,
    "likes": 155,
    "link": "https://www.krone.at/3233282",
    "image": "https://imgl.krone.at/scaled/2962830/v4cf8d2/full.jpg",
    "isAd": false
  },
  {
    "id": 149,
    "guid": "3231764",
    "title": "Pop-Hype des Jahres - The Last Dinner Party: Rückkehr des Pop-Anspruchs",
    "description": "Fünf junge Frauen kommen auf der Uni zusammen, eröffnen ein Konzert der Rolling Stones, gewinnen die...",
    "author": "Krone",
    "date": "2024-01-31 09:09",
    "comments": 1,
    "likes": 3,
    "link": "https://www.krone.at/3231764",
    "image": "https://imgl.krone.at/scaled/3231652/v57e883/full.jpg",
    "isAd": false
  },
  {
    "id": 150,
    "guid": "3233144",
    "title": "Kritische Debatte - 30 km/h im Ortsgebiet: „Nur mit Volksabstimmung“",
    "description": "Dass jeweils der Gemeinderat allein über ein striktes Tempolimit entscheiden kann, sieht die FPÖ als...",
    "author": "Krone",
    "date": "2024-01-31 09:00",
    "comments": 30,
    "likes": 189,
    "link": "https://www.krone.at/3233144",
    "image": "https://imgl.krone.at/scaled/3233146/vcc9fa3/full.jpg",
    "isAd": false
  },
  {
    "id": 151,
    "guid": "3233281",
    "title": "Mann zahlte nicht - Fahrgast flüchtete nach einer Taxifahrt",
    "description": "Wer kein Geld mehr hat, der sollte nicht mit dem Taxi fahren. Ein 24-jähriger Salzburger tat es trot...",
    "author": "Krone",
    "date": "2024-01-31 09:00",
    "comments": 19,
    "likes": 149,
    "link": "https://www.krone.at/3233281",
    "image": "https://imgl.krone.at/scaled/1991837/vc842b0/full.jpg",
    "isAd": false
  },
  {
    "id": 152,
    "guid": "3233247",
    "title": "Heute wartet Super-G - Speed-Prinzessin konnte Gold mit dem Papa feiern",
    "description": "Die 19-jährige Vorarlbergerin Victoria Olivier bescherte Österreich einen goldigen Auftakt der Junio...",
    "author": "Krone",
    "date": "2024-01-31 08:55",
    "comments": 1,
    "likes": 65,
    "link": "https://www.krone.at/3233247",
    "image": "https://imgl.krone.at/scaled/3233250/v6d99ad/full.jpg",
    "isAd": false
  },
  {
    "id": 153,
    "guid": "3233296",
    "title": "Körperteile im Kanal - „Stückelmord“: Verdächtiger war Geschäftspartner",
    "description": "Nachdem Körperteile eines Mannes kürzlich im Marchfeldkanal gefunden wurden, hat die Polizei nun am ...",
    "author": "Krone",
    "date": "2024-01-31 11:03",
    "comments": 4,
    "likes": 103,
    "link": "https://www.krone.at/3233296",
    "image": "https://imgl.krone.at/scaled/3233482/v6f4ec4/full.jpg",
    "isAd": false
  },
  {
    "id": 154,
    "guid": "3233278",
    "title": "Bei Zigarettenautomat - „Kevin“ zückte sein Messer: „I bring di um“",
    "description": "Eigentlich wollte er nur Zigaretten kaufen, doch für einen 22-Jährigen aus dem Bezirk Spittal endete...",
    "author": "Krone",
    "date": "2024-01-31 10:37",
    "comments": 1,
    "likes": 15,
    "link": "https://www.krone.at/3233278",
    "image": "https://imgl.krone.at/scaled/1651030/v41f974/full.jpg",
    "isAd": false
  },
  {
    "id": 155,
    "guid": "3233285",
    "title": "Das ging aber schnell - Nach nur einem Monat: Rune trennt sich von Coach",
    "description": "Das ging aber schnell! Nach nur einem Monat hat sich Tennis-Ass Holger Rune von seinem Trainer Sever...",
    "author": "Krone",
    "date": "2024-01-31 08:55",
    "comments": 18,
    "likes": 129,
    "link": "https://www.krone.at/3233285",
    "image": "https://imgl.krone.at/scaled/3233286/va1d4a0/full.jpg",
    "isAd": false
  },
  {
    "id": 156,
    "guid": "3233246",
    "title": "Keine Lizenz-Einigung - Universal Music will Musik von TikTok abziehen",
    "description": "Musik von Künstlern wie Taylor Swift oder Lady Gaga könnte ab Donnerstag aus der Video-App TikTok ve...",
    "author": "Krone",
    "date": "2024-01-31 08:40",
    "comments": 17,
    "likes": 164,
    "link": "https://www.krone.at/3233246",
    "image": "https://imgl.krone.at/scaled/3057175/vcdb476/full.jpg",
    "isAd": false
  },
  {
    "id": 157,
    "guid": "3233039",
    "title": "Anzeige von Ehemann - Verkäuferin drückte zu oft die Stornotaste",
    "description": "Aus Geldnot hatte eine Verkäuferin immer wieder in die Geschäftskasse einer Metzgerei gegriffen. Ihr...",
    "author": "Krone",
    "date": "2024-01-31 08:30",
    "comments": 1,
    "likes": 36,
    "link": "https://www.krone.at/3233039",
    "image": "https://imgl.krone.at/scaled/3232939/v3fbd28/full.jpg",
    "isAd": false
  },
  {
    "id": 158,
    "guid": "3233244",
    "title": "Kurioser Fall in Tirol - Flatscreen-Diebe auf Flucht selbst „bestohlen“",
    "description": "Man stelle sich vor, man stiehlt einen sündteuren 85-Zoll-Flatscreen aus einem Firmengebäude, und wi...",
    "author": "Krone",
    "date": "2024-01-31 08:40",
    "comments": 36,
    "likes": 181,
    "link": "https://www.krone.at/3233244",
    "image": "https://imgl.krone.at/scaled/722451/vfc0996/full.jpg",
    "isAd": false
  },
  {
    "id": 159,
    "guid": "3233240",
    "title": "Kremlkritische Band - Rockmusiker fürchten Abschiebung nach Russland",
    "description": "Nach einem Auftritt in Thailand muss eine regimekritische russische Rockband eine Abschiebung nach R...",
    "author": "Krone",
    "date": "2024-01-31 08:24",
    "comments": 18,
    "likes": 117,
    "link": "https://www.krone.at/3233240",
    "image": "https://imgl.krone.at/scaled/3233260/v73c220/full.jpg",
    "isAd": false
  },
  {
    "id": 160,
    "guid": "3233232",
    "title": "Hitzige Szenen - Kurz nach Sieg: Arsenal-Stars geraten aneinander",
    "description": "Arsenal hat am Dienstagabend einen knappen 2:1-Erfolg bei Nottingham Forest gefeiert - enorm wichtig...",
    "author": "Krone",
    "date": "2024-01-31 08:37",
    "comments": 13,
    "likes": 119,
    "link": "https://www.krone.at/3233232",
    "image": "https://imgl.krone.at/scaled/3233235/v722253/full.jpg",
    "isAd": false
  },
  {
    "id": 161,
    "guid": "3233241",
    "title": "„Unfassbare Summe“ - Musk muss um 56 Mrd. Dollar an Vergütung bangen",
    "description": "Elon Musk muss um sein 56 Milliarden Dollar schweres Vergütungspaket bangen, das er vor Jahren für s...",
    "author": "Krone",
    "date": "2024-01-31 08:20",
    "comments": 6,
    "likes": 115,
    "link": "https://www.krone.at/3233241",
    "image": "https://imgl.krone.at/scaled/2830384/v11da7a/full.jpg",
    "isAd": false
  },
  {
    "id": 162,
    "guid": "3233237",
    "title": "Täter flüchtig - Raubüberfall im Fröbelpark: 16-Jähriger verletzt",
    "description": "Im Fröbelpark im Grazer Lend überfielen zwei Täter am Dienstagabend einen 16 und einen 17-Jährigen. ...",
    "author": "Krone",
    "date": "2024-01-31 08:18",
    "comments": 1,
    "likes": 37,
    "link": "https://www.krone.at/3233237",
    "image": "https://imgl.krone.at/scaled/3082432/vd23cdc/full.jpg",
    "isAd": false
  },
  {
    "id": 163,
    "guid": "3233231",
    "title": "Gisele Bündchen:  - Supermodel trauert mit berührenden Worten um Mama",
    "description": "Mit einer berührenden Nachricht nimmt das brasilianische Supermodel Gisele Bündchen auf Instagram Ab...",
    "author": "Krone",
    "date": "2024-01-31 08:17",
    "comments": 4,
    "likes": 21,
    "link": "https://www.krone.at/3233231",
    "image": "https://imgl.krone.at/scaled/3233259/v3cb68d/full.jpg",
    "isAd": false
  },
  {
    "id": 164,
    "guid": "3233234",
    "title": "Kampf ums Finalticket - Österreichs Kaleen tritt im 2. ESC-Halbfinale an",
    "description": "Österreich startet heuer am 9. Mai im 2. Halbfinale in den 68. Eurovision Song Contest von Malmö. Di...",
    "author": "Krone",
    "date": "2024-01-31 08:09",
    "comments": 5,
    "likes": 70,
    "link": "https://www.krone.at/3233234",
    "image": "https://imgl.krone.at/scaled/3219017/vf17975/full.jpg",
    "isAd": false
  },
  {
    "id": 165,
    "guid": "3233121",
    "title": "Streng geheim - Sturm läutet den Countdown für die Austria ein",
    "description": "Sturms Cup-Generalprobe, ein 0:0 gegen Rukh Lviv, lief in Catez top secret ab. Coach Christian Ilzer...",
    "author": "Krone",
    "date": "2024-01-31 09:13",
    "comments": 22,
    "likes": 131,
    "link": "https://www.krone.at/3233121",
    "image": "https://imgl.krone.at/scaled/3233119/vd2ad8d/full.jpg",
    "isAd": false
  },
  {
    "id": 166,
    "guid": "3233005",
    "title": "Handys und Drogen - Schmuggel-Krimi in Graz: Beamte sitzen in U-Haft",
    "description": "Richtig tief in der Patsche sitzen aktuell zwei Beamte der Grazer Justizanstalt Karlau. Die beiden s...",
    "author": "Krone",
    "date": "2024-01-31 11:04",
    "comments": 10,
    "likes": 80,
    "link": "https://www.krone.at/3233005",
    "image": "https://imgl.krone.at/scaled/1995206/v6db4d0/full.jpg",
    "isAd": false
  },
  {
    "id": 167,
    "guid": "3232942",
    "title": "Flachgauer Bahntunnel - Angst der Baustellen-Anrainer vor Staub und Lärm",
    "description": "Für die Gemeinde Köstendorf sind die Unterlagen zur Umweltprüfung des Bahntunnels durch den Flachgau...",
    "author": "Krone",
    "date": "2024-01-31 08:00",
    "comments": 18,
    "likes": 99,
    "link": "https://www.krone.at/3232942",
    "image": "https://imgl.krone.at/scaled/3232944/vf75fcb/full.jpg",
    "isAd": false
  },
  {
    "id": 168,
    "guid": "3232981",
    "title": "Nach Schicksalschlag - Ortschef kehrt mit 31 Jahren Politik den Rücken zu",
    "description": "Paukenschlag in der vierkleinsten Gemeinde Oberösterreichs. Nach  einem Schicksalsschlag im Vorjahr ...",
    "author": "Krone",
    "date": "2024-01-31 08:00",
    "comments": 14,
    "likes": 164,
    "link": "https://www.krone.at/3232981",
    "image": "https://imgl.krone.at/scaled/3232985/vcd4165/full.jpg",
    "isAd": false
  },
  {
    "id": 169,
    "guid": "3233238",
    "title": "Staatlicher Eingriff - Panne in Russland: .ru-Websites nicht erreichbar",
    "description": "Millionen Mobilfunknutzer in Russland haben am Dienstag mit dem Zugang zu Internetseiten oder Apps d...",
    "author": "Krone",
    "date": "2024-01-31 07:58",
    "comments": 4,
    "likes": 64,
    "link": "https://www.krone.at/3233238",
    "image": "https://imgl.krone.at/scaled/2035419/v08cb8c/full.jpg",
    "isAd": false
  },
  {
    "id": 170,
    "guid": "3232861",
    "title": "Bub (14) vor Gericht - Kaugummi-Automaten mit Bunsenbrenner geknackt",
    "description": "Ein 14-jähriger Bub hatte in Tirol offenbar Lust auf Kaugummis und versuchte sich diese auf feurige ...",
    "author": "Krone",
    "date": "2024-01-31 08:54",
    "comments": 13,
    "likes": 69,
    "link": "https://www.krone.at/3232861",
    "image": "https://imgl.krone.at/scaled/3232862/v194416/full.jpg",
    "isAd": false
  },
  {
    "id": 171,
    "guid": "3233219",
    "title": "Streit eskalierte - Drogenpärchen: Mann biss und schlug seine Freundin",
    "description": "In der Nacht auf Mittwoch eskalierte ein Beziehungsstreit eines Klagenfurter Pärchens völlig. Wegen ...",
    "author": "Krone",
    "date": "2024-01-31 07:52",
    "comments": 1,
    "likes": 4,
    "link": "https://www.krone.at/3233219",
    "image": "https://imgl.krone.at/scaled/2195289/v8001db/full.jpg",
    "isAd": false
  },
  {
    "id": 172,
    "guid": "3233229",
    "title": "Nach Horror-Sturz: - „Mein Knochen fängt endlich an, zusammenzuwachsen“",
    "description": "Max Franz, der sich im November 2022 bei einem Trainingssturz in den USA beide Beine brach, gibt ein...",
    "author": "Krone",
    "date": "2024-01-31 08:49",
    "comments": 12,
    "likes": 158,
    "link": "https://www.krone.at/3233229",
    "image": "https://imgl.krone.at/scaled/3233230/va259d9/full.jpg",
    "isAd": false
  },
  {
    "id": 173,
    "guid": "3233220",
    "title": "200 Küken tot - Vogelgrippe bedroht Pinguine auf Falklandinseln",
    "description": "Das Vogelgrippe-Virus breitet sich im Südatlantik weiter aus. Die Regierung der Falklandinseln teilt...",
    "author": "Krone",
    "date": "2024-01-31 07:22",
    "comments": 28,
    "likes": 195,
    "link": "https://www.krone.at/3233220",
    "image": "https://imgl.krone.at/scaled/1650933/v8b77f0/full.jpg",
    "isAd": false
  },
  {
    "id": 174,
    "guid": "3233217",
    "title": "Foto aus Spital - Schlimmer Sturz: MotoGP-Star verliert Bewusstsein",
    "description": "Franco Morbidelli ist am Dienstag im Training in Portimao schwer gestürzt. Beim Crash verlor der Pra...",
    "author": "Krone",
    "date": "2024-01-31 07:36",
    "comments": 4,
    "likes": 53,
    "link": "https://www.krone.at/3233217",
    "image": "https://imgl.krone.at/scaled/3233218/vb345d8/full.jpg",
    "isAd": false
  },
  {
    "id": 175,
    "guid": "3233214",
    "title": "Gegen Rechts und Ball - Jetzt kommen zwei Demo-Wochenenden in Linz",
    "description": "An den kommenden beiden Wochenenden sind in Linz zwei Kundgebungen geplant: Fast schon traditionell ...",
    "author": "Krone",
    "date": "2024-01-31 16:29",
    "comments": 15,
    "likes": 179,
    "link": "https://www.krone.at/3233214",
    "image": "https://imgl.krone.at/scaled/1856079/vd0dabe/full.jpg",
    "isAd": false
  },
  {
    "id": 176,
    "guid": "3232710",
    "title": "Coach Stephan Helm: - Besser als Flick! Aber „vielleicht auch naiv“",
    "description": "Wo läuft Stephan Helm dem ehemaligen DFB-Coach Hansi Flick den Rang ab? Beim Punkteschnitt! Und was ...",
    "author": "Krone",
    "date": "2024-01-31 07:00",
    "comments": 33,
    "likes": 193,
    "link": "https://www.krone.at/3232710",
    "image": "https://imgl.krone.at/scaled/3232719/v8c61a0/full.jpg",
    "isAd": false
  },
  {
    "id": 177,
    "guid": "3232914",
    "title": "Immobilien-Spekulation - Aus für Pension: Menschen stehen auf der Straße",
    "description": "Das „Haus Oberdossen“ in Salzburg-Gneis schließt, der Eigentümer plant, anstatt der Sozialpensionen ...",
    "author": "Krone",
    "date": "2024-01-31 07:00",
    "comments": 4,
    "likes": 121,
    "link": "https://www.krone.at/3232914",
    "image": "https://imgl.krone.at/scaled/3232922/v1ca991/full.jpg",
    "isAd": false
  },
  {
    "id": 178,
    "guid": "3232891",
    "title": "Kinostart - Eine berührende Reise zurück ins Leben",
    "description": "„Eine Million Minuten“ wünscht sich ein junges Mädchen im gleichnamigen Kinofilm von ihren Eltern. W...",
    "author": "Krone",
    "date": "2024-01-31 07:00",
    "comments": 7,
    "likes": 131,
    "link": "https://www.krone.at/3232891",
    "image": "https://imgl.krone.at/scaled/3232904/v2f4c51/full.jpg",
    "isAd": false
  },
  {
    "id": 179,
    "guid": "3232591",
    "title": "1. Society-Auftritt - Volkslied-Gigant Heino adelt den Wiener Opernball",
    "description": "Er eilt aktuell von Erfolg zu Erfolg im Zuge seiner Kirchen-Tour. Er tut es für seine Fans und für s...",
    "author": "Krone",
    "date": "2024-01-31 09:31",
    "comments": 19,
    "likes": 194,
    "link": "https://www.krone.at/3232591",
    "image": "https://imgl.krone.at/scaled/3232580/v8e0fba/full.jpg",
    "isAd": false
  },
  {
    "id": 180,
    "guid": "3198273",
    "title": "Leseraktionen - Die schönsten Sehenswürdigkeiten",
    "description": "Es muss nicht gleich das Riesenrad in Wien oder der Lindwurm in Klagenfurt sein - jede Stadt hat Ihr...",
    "author": "Krone",
    "date": "2024-01-31 07:00",
    "comments": 10,
    "likes": 81,
    "link": "https://www.krone.at/3198273",
    "image": "https://imgl.krone.at/scaled/1546625/v519969/full.jpg",
    "isAd": false
  },
  {
    "id": 181,
    "guid": "3233028",
    "title": "Große Auszeichnung - Steirisches Weingut als beliebtester Hochzeitsort",
    "description": "Der Familienbetrieb Kolleritsch in Tieschen hat österreichweit die Nase vorne – der gefragteste Tag ...",
    "author": "Krone",
    "date": "2024-01-31 07:00",
    "comments": 27,
    "likes": 165,
    "link": "https://www.krone.at/3233028",
    "image": "https://imgl.krone.at/scaled/3233029/vf70dd0/full.jpg",
    "isAd": false
  },
  {
    "id": 182,
    "guid": "3232617",
    "title": "Post an den Kanzler - Tierschutzgesetz: Ihr Mail an die Regierung zählt!",
    "description": "Ein Zusammenschluss aus mehreren Tierschutzorganisationen fordert die Umsetzung einer überfälligen G...",
    "author": "Krone",
    "date": "2024-01-31 06:58",
    "comments": 3,
    "likes": 49,
    "link": "https://www.krone.at/3232617",
    "image": "https://imgl.krone.at/scaled/3225655/vac354b/full.jpg",
    "isAd": false
  },
  {
    "id": 183,
    "guid": "3233213",
    "title": "Nur noch Trümmer - Satellitendaten: Hälfte der Gaza-Gebäude zerstört",
    "description": "Fast vier Monate nach Kriegsbeginn im Gazastreifen ist bereits mindestens die Hälfte aller Gebäude n...",
    "author": "Krone",
    "date": "2024-01-31 08:00",
    "comments": 14,
    "likes": 119,
    "link": "https://www.krone.at/3233213",
    "image": "https://imgl.krone.at/scaled/3233216/v0fa317/full.jpg",
    "isAd": false
  },
  {
    "id": 184,
    "guid": "3233209",
    "title": "Schon zweiter Vorfall - US-Kampfjet über Meer abgestürzt - Pilot überlebte",
    "description": "Binnen weniger Wochen ist erneut ein F-16-Kampfjet der US-Streitkräfte in Südkorea während eines Flu...",
    "author": "Krone",
    "date": "2024-01-31 06:33",
    "comments": 6,
    "likes": 99,
    "link": "https://www.krone.at/3233209",
    "image": "https://imgl.krone.at/scaled/3233210/v376cc2/full.jpg",
    "isAd": false
  },
  {
    "id": 185,
    "guid": "3233207",
    "title": "Kurze Verfolgungsjagd - Kärntner Dealer wollte Gras über Grenze schmuggeln",
    "description": "Immer wieder hört man von importierter Drogenkriminalität, aber am Dienstag nahm ein 38-jähriger Kär...",
    "author": "Krone",
    "date": "2024-01-31 12:55",
    "comments": 9,
    "likes": 89,
    "link": "https://www.krone.at/3233207",
    "image": "https://imgl.krone.at/scaled/3233627/ve555cf/full.jpg",
    "isAd": false
  },
  {
    "id": 186,
    "guid": "3233208",
    "title": "„Gibt keinen Kontakt“ - Sturm: Schicker dementiert Gerücht um Kiteishvili",
    "description": "Das Transferfenster verlief aus Sicht von Sturm Graz bislang ruhig, mit Angreifer Mika Biereth und T...",
    "author": "Krone",
    "date": "2024-01-31 06:23",
    "comments": 10,
    "likes": 103,
    "link": "https://www.krone.at/3233208",
    "image": "https://imgl.krone.at/scaled/3115111/v5e8861/full.jpg",
    "isAd": false
  },
  {
    "id": 187,
    "guid": "3233205",
    "title": "Superstar außer Form? - Jetzt schießt „fetter“ Neymar gegen seine Kritiker",
    "description": "Neymar außer Form? Das Gewicht des Superstars war zuletzt ein großes Gesprächsthema bei den Fans. Je...",
    "author": "Krone",
    "date": "2024-01-31 06:15",
    "comments": 1,
    "likes": 8,
    "link": "https://www.krone.at/3233205",
    "image": "https://imgl.krone.at/scaled/3233206/v8c5f26/full.jpg",
    "isAd": false
  },
  {
    "id": 188,
    "guid": "3232966",
    "title": "Immer mehr Einsätze - Florianis gingen für uns 72.000-mal durchs Feuer",
    "description": "Die Bilanz 2023 fordert Anerkennung: Mit einem Einsatzplus von elf Prozent stellen Ehrenamtliche in ...",
    "author": "Krone",
    "date": "2024-01-31 06:08",
    "comments": 4,
    "likes": 198,
    "link": "https://www.krone.at/3232966",
    "image": "https://imgl.krone.at/scaled/3232967/v37cbe8/full.jpg",
    "isAd": false
  },
  {
    "id": 189,
    "guid": "3232863",
    "title": "Ukrainer erschöpft - Soldat: „Noch kein Licht am Ende des Tunnels“",
    "description": "In voller Montur, die Mütze über den Augen, schläft ein ukrainischer Soldat auf einer Pritsche in ei...",
    "author": "Krone",
    "date": "2024-01-31 07:25",
    "comments": 4,
    "likes": 51,
    "link": "https://www.krone.at/3232863",
    "image": "https://imgl.krone.at/scaled/3232871/v6743d7/full.jpg",
    "isAd": false
  },
  {
    "id": 190,
    "guid": "3232572",
    "title": "Format für Blinde - Tasten, fühlen, riechen im Kunsthaus Bregenz",
    "description": "Das Kunsthaus Bregenz (Vorarlberg) bietet nun auch Führungen für Menschen mit Sehbehinderung an. Die...",
    "author": "Krone",
    "date": "2024-01-31 06:05",
    "comments": 8,
    "likes": 82,
    "link": "https://www.krone.at/3232572",
    "image": "https://imgl.krone.at/scaled/3232577/v02092e/full.jpg",
    "isAd": false
  },
  {
    "id": 191,
    "guid": "3232466",
    "title": "Ukrainischer Koloss - Wie aus Lenin ein großer Waldviertler wurde",
    "description": "Einzigartiges, skurriles und außergewöhnliches Kulturgut - das steht bei Sammler Christian Berger ga...",
    "author": "Krone",
    "date": "2024-01-31 06:00",
    "comments": 6,
    "likes": 127,
    "link": "https://www.krone.at/3232466",
    "image": "https://imgl.krone.at/scaled/3232850/vef9fe4/full.jpg",
    "isAd": false
  },
  {
    "id": 192,
    "guid": "3232773",
    "title": "Buch gibt Tipps - Ein Kompass für den nachhaltigen Familienalltag",
    "description": "„Krone“-Kolumnistin Daniela Gaigg gibt in ihrem neuen Buch Tipps und Tricks für einen nachhaltigen A...",
    "author": "Krone",
    "date": "2024-01-31 06:00",
    "comments": 8,
    "likes": 62,
    "link": "https://www.krone.at/3232773",
    "image": "https://imgl.krone.at/scaled/3232776/v16f2e9/full.jpg",
    "isAd": false
  },
  {
    "id": 193,
    "guid": "3233085",
    "title": "Falle zugeschnappt - Cyber-Bande zweigte Geld von Sportverein ab",
    "description": "Ins Visier von Cyber-Kriminellen ist ein Fußballclub im Bezirk Oberwart geraten. Per „Hacker-Trick“ ...",
    "author": "Krone",
    "date": "2024-01-31 06:00",
    "comments": 1,
    "likes": 6,
    "link": "https://www.krone.at/3233085",
    "image": "https://imgl.krone.at/scaled/3233086/vf59d1f/full.jpg",
    "isAd": false
  },
  {
    "id": 194,
    "guid": "3233130",
    "title": "Klagenfurter Budget - „Sind pleite und ein Fall für den Konkursrichter“",
    "description": "Dass im Klagenfurter Rathaus Streit auf der Tagesordnung steht, ist bekannt. Doch bei der Gemeindera...",
    "author": "Krone",
    "date": "2024-01-31 06:00",
    "comments": 18,
    "likes": 195,
    "link": "https://www.krone.at/3233130",
    "image": "https://imgl.krone.at/scaled/3213411/vf36a2b/full.jpg",
    "isAd": false
  },
  {
    "id": 195,
    "guid": "3232848",
    "title": "Austrias „Zweier“ Kos - Auf Eisbad folgt Tanz gegen Titelverteidiger",
    "description": "Auf das Eisbad folgt der heiße Tanz gegen den Titelverteidiger: Austrias „Zweier“ Mirko Kos wird am ...",
    "author": "Krone",
    "date": "2024-01-31 06:00",
    "comments": 7,
    "likes": 160,
    "link": "https://www.krone.at/3232848",
    "image": "https://imgl.krone.at/scaled/3232857/vc8b6d8/full.jpg",
    "isAd": false
  },
  {
    "id": 196,
    "guid": "3232680",
    "title": "LAUF-ASSE IN AFRIKA - Vom höchsten Niveau direkt zum Wettkampf",
    "description": "Afrika ist um diese Jahreszeit ein Hotspot für Ausdauersportler. Auch bei den heimischen Lauf-Assen ...",
    "author": "Krone",
    "date": "2024-01-31 06:00",
    "comments": 7,
    "likes": 42,
    "link": "https://www.krone.at/3232680",
    "image": "https://imgl.krone.at/scaled/3232668/vdb465d/full.jpg",
    "isAd": false
  },
  {
    "id": 197,
    "guid": "3232932",
    "title": "Dramatische OP im AKH - Nach Aortariss hing Leben an wenigen Herzschlägen",
    "description": "Durch eine dramatische Rettungsaktion und eine ärztliche Topleistung wurde ein Patient im Wiener AKH...",
    "author": "Krone",
    "date": "2024-01-31 08:44",
    "comments": 13,
    "likes": 103,
    "link": "https://www.krone.at/3232932",
    "image": "https://imgl.krone.at/scaled/3232952/v49d879/full.jpg",
    "isAd": false
  },
  {
    "id": 198,
    "guid": "3232808",
    "title": "Alle Bezirke im Detail - Halb Wien darf neues Parlament nicht wählen",
    "description": "In der Zwei-Millionen-Stadt können nur noch 1,13 Millionen Wiener bei der kommenden Nationalratswahl...",
    "author": "Krone",
    "date": "2024-01-31 08:32",
    "comments": 13,
    "likes": 116,
    "link": "https://www.krone.at/3232808",
    "image": "https://imgl.krone.at/scaled/3232807/vcae273/full.jpg",
    "isAd": false
  },
  {
    "id": 199,
    "guid": "3232741",
    "title": "Jetzt Wirbel um Kosten - „Haben sich ja nicht mit Goldstaub eingepudert!“",
    "description": "Im Internet tauchen absurde Zahlen auf, dass der „Skandaltanz“ von Bad Ischl elf Millionen Euro geko...",
    "author": "Krone",
    "date": "2024-01-31 06:00",
    "comments": 18,
    "likes": 123,
    "link": "https://www.krone.at/3232741",
    "image": "https://imgl.krone.at/scaled/3232740/v8323ce/full.jpg",
    "isAd": false
  },
  {
    "id": 200,
    "guid": "3232915",
    "title": "Salzburgs Wirtesterben - Weiserhof-Chef schließt: „Ich kann nicht mehr!“",
    "description": "Corona und Personalmangel in ganz Österreich: Das Wirtesterben - nicht nur in Salzburg - geht weiter...",
    "author": "Krone",
    "date": "2024-01-31 06:00",
    "comments": 1,
    "likes": 173,
    "link": "https://www.krone.at/3232915",
    "image": "https://imgl.krone.at/scaled/3232918/v851de6/full.jpg",
    "isAd": false
  }
]